Workbook
Name Slicer_Month: #N/A
Name Slicer_Month1: #N/A
Name Slicer_Month2: #N/A
Name Slicer_Month3: #N/A

Sheet Total Expenses(Chart)
A1: Row Labels | B1: Sum of Salary to be Paid
A2: Consultant | B2: 0.12287441
A3: Employee | B3: 0.87712559
A4: Grand Total | B4: 1

Sheet HR&Consultant
A1: Row Labels | B1: Sum of Salary to be Paid
A2: Consultant | B2: 720147
A3: Grand Total | B3: 720147

Sheet SSPL
A1: Sr. No. | B1: Employee Name | C1: Notes | D1: Employee Code | E1: Working Days | F1: Employee Working Days | G1: Taken Leave | H1: Deductible Leave | I1: Salary after Leave Deduction | J1: Employee Type | K1: PF | L1: ESI | M1: NPS | N1: Professional TAX | O1: Total Deduction | P1: Difference from Last Month / Advance Pay / Loan EMI | Q1: Bonus / Encashment / Reimbursment | R1: TDS | S1: Other Deduction/Salary Hold | T1: Salary to be Paid
A2: 1 | B2: Ajay Jikadra | D2: 297 | E2: 22 | F2: 22 | G2: 0 | H2: 0 | I2: 50000 | J2: Employee | K2: 3600 | L2: 2000 | M2: 0 | N2: 0 | O2: 5600 | R2: 0 | T2: 44400
A3: 2 | B3: Ajay Khavas | C3: DOJ 9th Mar | D3: 304 | E3: 22 | F3: 17 | G3: 0 | H3: 0 | I3: 38636.364 | J3: Employee | K3: 0 | L3: 0 | M3: 0 | N3: 200 | O3: 200 | R3: 0 | T3: 38436
A4: 3 | B4: Akanshi Jain | C4: Parttime Consultant | E4: 22 | F4: 22 | G4: 0 | H4: 0 | I4: 50000 | J4: Consultant | K4: 0 | L4: 0 | M4: 0 | N4: 0 | O4: 0 | R4: 500 | T4: 49500
A5: 4 | B5: Akash Rathor | D5: 249 | E5: 22 | F5: 22 | G5: 1 | H5: 0 | I5: 50000 | J5: Employee | K5: 0 | L5: 0 | M5: 0 | N5: 200 | O5: 200 | R5: 0 | T5: 49800
A6: 5 | B6: Akash Sheth | D6: 273 | E6: 22 | F6: 22 | G6: 0 | H6: 0 | I6: 50000 | J6: Employee | K6: 3600 | L6: 0 | M6: 1250 | N6: 200 | O6: 5050 | R6: 3303 | T6: 41647
A7: 6 | B7: Akshay Patel | D7: 264 | E7: 22 | F7: 22 | G7: 1 | H7: 0 | I7: 50000 | J7: Employee | K7: 3600 | L7: 0 | M7: 0 | N7: 200 | O7: 3800 | R7: 3256 | T7: 42944
A8: 7 | B8: Amir Khan | C8: DOJ 20th Mar | D8: 309 | E8: 22 | F8: 10 | G8: 0 | H8: 0 | I8: 22727.273 | J8: Employee | K8: 0 | L8: 0 | M8: 0 | N8: 200 | O8: 200 | R8: 0 | T8: 22527
A9: 8 | B9: Anandi Pattani | D9: 276 | E9: 22 | F9: 22 | G9: 1 | H9: 0 | I9: 50000 | J9: Employee | K9: 0 | L9: 0 | M9: 0 | N9: 200 | O9: 200 | R9: 0 | T9: 49800
A10: 9 | B10: Anil Babubhai Variya | D10: 164 | E10: 22 | F10: 22 | G10: 0.5 | H10: 0 | I10: 50000 | J10: Employee | K10: 0 | L10: 0 | M10: 0 | N10: 200 | O10: 200 | Q10: 16138 | R10: 14016 | T10: 51922
A11: 10 | B11: Ankit Donda | C11: Freelancer | E11: 22 | F11: 22 | G11: 0 | H11: 0 | I11: 50000 | J11: Consultant | K11: 0 | L11: 0 | M11: 0 | N11: 0 | O11: 0 | R11: 500 | T11: 49500
A12: 11 | B12: Ankit Prajapati | D12: 236 | E12: 22 | F12: 22 | G12: 0 | H12: 0 | I12: 50000 | J12: Employee | K12: 0 | L12: 0 | M12: 0 | N12: 200 | O12: 200 | R12: 17900 | T12: 31900
A13: 12 | B13: Ankita Bharat Ranpariya | C13: Freelancer | E13: 22 | F13: 22 | G13: 0 | H13: 0 | I13: 50000 | J13: Consultant | K13: 0 | L13: 0 | M13: 0 | N13: 0 | O13: 0 | R13: 500 | T13: 49500
A14: 13 | B14: Ankita Damani | C14: Salary Already Paid | E14: 22 | F14: 22 | G14: 0 | H14: 0 | I14: 50000 | J14: Employee | K14: 0 | L14: 0 | M14: 0 | N14: 200 | O14: 200 | R14: 0 | T14: 49800
A15: 14 | B15: Ankur Paranjpe | D15: 294 | E15: 22 | F15: 22 | G15: 0 | H15: 0 | I15: 50000 | J15: Employee | K15: 3600 | L15: 0 | M15: 0 | N15: 200 | O15: 3800 | R15: 24906 | T15: 21294
A16: 15 | B16: Anmol Hariombhai Chaudhary | D16: 151 | E16: 22 | F16: 22 | G16: 0 | H16: 0 | I16: 50000 | J16: Employee | K16: 0 | L16: 0 | M16: 0 | N16: 200 | O16: 200 | R16: 7626 | T16: 42174
A17: 16 | B17: Arjun Lal Rabari | D17: 116 | E17: 22 | F17: 22 | G17: 0 | H17: 0 | I17: 50000 | J17: Employee | K17: 3600 | L17: 2000 | M17: 0 | N17: 200 | O17: 5800 | P17: 15000 | R17: 0 | T17: 29200
A18: 17 | B18: Arpita Harshadbhai Patel | D18: 140 | E18: 22 | F18: 22 | G18: 2 | H18: 0 | I18: 50000 | J18: Employee | K18: 0 | L18: 0 | M18: 0 | N18: 200 | O18: 200 | R18: 0 | T18: 49800
A19: 18 | B19: ARTI CHINTAN KOTHARI | C19: Salary Already Paid | E19: 22 | F19: 22 | G19: 0 | H19: 0 | I19: 50000 | J19: Employee | K19: 0 | L19: 0 | M19: 0 | N19: 200 | O19: 200 | R19: 0 | T19: 49800
A20: 19 | B20: Ashish Mansukhbhai Chaniyara | D20: 141 | E20: 22 | F20: 22 | G20: 1.5 | H20: 0 | I20: 50000 | J20: Employee | K20: 0 | L20: 0 | M20: 0 | N20: 200 | O20: 200 | R20: 0 | T20: 49800
A21: 20 | B21: Ashish Sharma | D21: 257 | E21: 22 | F21: 22 | G21: 0 | H21: 0 | I21: 50000 | J21: Employee | K21: 0 | L21: 0 | M21: 0 | N21: 200 | O21: 200 | R21: 12599 | T21: 37201
A22: 21 | B22: Ashwin Narendrabhai Patel | D22: 42 | E22: 22 | F22: 22 | G22: 0 | H22: 0 | I22: 50000 | J22: Employee | K22: 0 | L22: 0 | M22: 0 | N22: 200 | O22: 200 | R22: 0 | T22: 49800
A23: 22 | B23: Avaiya Dharmeshkumar Haribhai | C23: Freelancer | E23: 22 | F23: 22 | G23: 0 | H23: 0 | I23: 50000 | J23: Consultant | K23: 0 | L23: 0 | M23: 0 | N23: 0 | O23: 0 | R23: 500 | T23: 49500
A24: 23 | B24: Avani Ashvinbhai Patel | D24: 66 | E24: 22 | F24: 22 | G24: 0 | H24: 0 | I24: 50000 | J24: Employee | K24: 3600 | L24: 0 | M24: 0 | N24: 200 | O24: 3800 | P24: 22222 | R24: 12000 | T24: 11978
A25: 24 | B25: Bansi Gothi | D25: 269 | E25: 22 | F25: 22 | G25: 0 | H25: 0 | I25: 50000 | J25: Employee | K25: 0 | L25: 0 | M25: 0 | N25: 200 | O25: 200 | R25: 0 | T25: 49800
A26: 25 | B26: Bansi Jayantibhai Sojitra | D26: 4 | E26: 22 | F26: 22 | G26: 0 | H26: 0 | I26: 50000 | J26: Employee | K26: 0 | L26: 0 | M26: 0 | N26: 200 | O26: 200 | R26: 0 | T26: 49800
A27: 26 | B27: Bharat Kadchha | D27: 225 | E27: 22 | F27: 22 | G27: 6 | H27: 0 | I27: 50000 | J27: Employee | K27: 3600 | L27: 0 | M27: 0 | N27: 200 | O27: 3800 | R27: 0 | T27: 46200
A28: 27 | B28: Bhartiben Italiya | C28: Salary Already Paid | E28: 22 | F28: 22 | G28: 0 | H28: 0 | I28: 50000 | J28: Employee | K28: 0 | L28: 0 | M28: 0 | N28: 200 | O28: 200 | R28: 0 | T28: 49800
A29: 28 | B29: Bhatt Krupa Pradipbhai | D29: 165 | E29: 22 | F29: 22 | G29: 2 | H29: 0 | I29: 50000 | J29: Employee | K29: 0 | L29: 0 | M29: 0 | N29: 200 | O29: 200 | R29: 0 | T29: 49800
A30: 29 | B30: Bhavik Kiri | D30: 300 | E30: 22 | F30: 22 | G30: 0 | H30: 0 | I30: 50000 | J30: Employee | K30: 3600 | L30: 0 | M30: 0 | N30: 200 | O30: 3800 | R30: 0 | T30: 46200
A31: 30 | B31: Bhumi Shah | D31: 255 | E31: 22 | F31: 22 | G31: 1 | H31: 0 | I31: 50000 | J31: Employee | K31: 3600 | L31: 0 | M31: 0 | N31: 200 | O31: 3800 | R31: 0 | T31: 46200
A32: 31 | B32: Bikash Harenhandra Bhakat | D32: 131 | E32: 22 | F32: 22 | G32: 1.5 | H32: 0 | I32: 50000 | J32: Employee | K32: 3600 | L32: 0 | M32: 1250 | N32: 200 | O32: 5050 | R32: 0 | T32: 44950
A33: 32 | B33: Binal Rajeshbhai Kharecha | D33: 22 | E33: 22 | F33: 22 | G33: 0.5 | H33: 0 | I33: 50000 | J33: Employee | K33: 0 | L33: 0 | M33: 0 | N33: 200 | O33: 200 | R33: 0 | T33: 49800
A34: 33 | B34: Chaitali Deepakbhai Zaveri | C34: Resigned on 17th Feb-Salary on Hold | E34: 22 | F34: 22 | G34: 0 | H34: 0 | I34: 50000 | J34: Employee | K34: 3600 | L34: 0 | M34: 0 | N34: 200 | O34: 3800 | R34: 0 | T34: 46200
A35: 34 | B35: Chaitnya Parikh | C35: Last Salary F&F | E35: 22 | F35: 12 | G35: 0 | H35: 0 | I35: 27272.727 | J35: Employee | K35: 3600 | L35: 0 | M35: 0 | N35: 200 | O35: 3800 | R35: 0 | T35: 23473
A36: 35 | B36: Chaitrali Gajjar | C36: DOJ 9th Mar | D36: 305 | E36: 22 | F36: 17 | G36: 1 | H36: 0 | I36: 38636.364 | J36: Employee | K36: 0 | L36: 0 | M36: 0 | N36: 200 | O36: 200 | R36: 0 | T36: 38436
A37: 36 | B37: Chetana Ramasare Ravat | D37: 137 | E37: 22 | F37: 22 | G37: 1 | H37: 0 | I37: 50000 | J37: Employee | K37: 3600 | L37: 0 | M37: 0 | N37: 200 | O37: 3800 | P37: 33333 | R37: 0 | T37: 12867
A38: 37 | B38: Chirag Gujarati | D38: 274 | E38: 22 | F38: 22 | G38: 0 | H38: 0 | I38: 50000 | J38: Employee | K38: 3600 | L38: 0 | M38: 0 | N38: 200 | O38: 3800 | R38: 0 | T38: 46200
A39: 38 | B39: Darshan Rasikbhai Chudasama | D39: 90 | E39: 22 | F39: 22 | G39: 6 | H39: 0 | I39: 50000 | J39: Employee | K39: 3600 | L39: 0 | M39: 0 | N39: 200 | O39: 3800 | R39: 13325 | T39: 32875
A40: 39 | B40: Darshana Patel | D40: 90 | E40: 22 | F40: 22 | G40: 0 | H40: 0 | I40: 50000 | J40: Employee | K40: 0 | L40: 0 | M40: 0 | N40: 200 | O40: 200 | P40: 34800 | R40: 0 | T40: 15000
A41: 40 | B41: Desai Nayanaben Rutul Kumar | C41: Parttime Consultant | E41: 22 | F41: 4 | G41: 0 | H41: 0 | I41: 9090.9091 | J41: Consultant | K41: 0 | L41: 0 | M41: 0 | N41: 0 | O41: 0 | R41: 91 | T41: 9000
A42: 41 | B42: Dhananjay Rajeshbhai Dhobi | D42: 9 | E42: 22 | F42: 22 | G42: 1 | H42: 0 | I42: 50000 | J42: Employee | K42: 3600 | L42: 0 | M42: 0 | N42: 200 | O42: 3800 | P42: 29167 | R42: 7895 | T42: 9138
A43: 42 | B43: Dhara Mansukhbhai Basida | C43: Resigned on 17th Mar-Salary on Hold | D43: 128 | E43: 22 | F43: 22 | G43: 2 | H43: 2 | I43: 45454.545 | J43: Employee | K43: 3600 | L43: 0 | M43: 0 | N43: 200 | O43: 3800 | P43: 36000 | R43: 0 | T43: 5655
A44: 43 | B44: Dheeraj Chadhar | D44: 262 | E44: 22 | F44: 22 | G44: 1 | H44: 0 | I44: 50000 | J44: Employee | K44: 3600 | L44: 0 | M44: 0 | N44: 200 | O44: 3800 | R44: 0 | T44: 46200
A45: 44 | B45: Dhruvi Damani | C45: Salary Already Paid | E45: 22 | F45: 22 | G45: 0 | H45: 0 | I45: 50000 | J45: Employee | K45: 0 | L45: 0 | M45: 0 | N45: 200 | O45: 200 | R45: 0 | T45: 49800
A46: 45 | B46: Dhwani Shah | E46: 22 | F46: 22 | G46: 0 | H46: 0 | I46: 50000 | J46: Employee | K46: 0 | L46: 0 | M46: 0 | N46: 200 | O46: 200 | R46: 0 | T46: 49800
A47: 46 | B47: Digvijaysinh Zankat | D47: 280 | E47: 22 | F47: 22 | G47: 1 | H47: 0 | I47: 50000 | J47: Employee | K47: 3600 | L47: 0 | M47: 0 | N47: 200 | O47: 3800 | R47: 0 | T47: 46200
A48: 47 | B48: DISHA SANANDIYA | C48: Salary Already Paid | E48: 22 | F48: 22 | G48: 0 | H48: 0 | I48: 50000 | J48: Employee | K48: 0 | L48: 0 | M48: 0 | N48: 200 | O48: 200 | R48: 0 | T48: 49800
A49: 48 | B49: Dolly Dinesh Kumar Shah | D49: 132 | E49: 22 | F49: 22 | G49: 0 | H49: 0 | I49: 50000 | J49: Employee | K49: 0 | L49: 0 | M49: 0 | N49: 200 | O49: 200 | R49: 0 | T49: 49800
A50: 49 | B50: Fatema Dungarawala | D50: 243 | E50: 22 | F50: 22 | G50: 2 | H50: 0 | I50: 50000 | J50: Employee | K50: 0 | L50: 0 | M50: 0 | N50: 200 | O50: 200 | R50: 4753 | T50: 45047
A51: 50 | B51: Fenil Kanjiya | C51: DOJ 14th Mar | D51: 306 | E51: 22 | F51: 14 | G51: 0 | H51: 0 | I51: 31818.182 | J51: Employee | K51: 3600 | L51: 1272.7273 | M51: 0 | N51: 0 | O51: 4872.7273 | R51: 0 | T51: 26945
A52: 51 | B52: Hardik Vaghela | D52: 270 | E52: 22 | F52: 22 | G52: 1 | H52: 0 | I52: 50000 | J52: Employee | K52: 3600 | L52: 0 | M52: 0 | N52: 200 | O52: 3800 | R52: 0 | T52: 46200
A53: 52 | B53: Harsh Goyal | D53: 247 | E53: 22 | F53: 22 | G53: 0 | H53: 0 | I53: 50000 | J53: Employee | K53: 3600 | L53: 0 | M53: 0 | N53: 200 | O53: 3800 | R53: 0 | T53: 46200
A54: 53 | B54: Harsha Sharma | D54: 241 | E54: 22 | F54: 22 | G54: 1 | H54: 0 | I54: 50000 | J54: Employee | K54: 3600 | L54: 0 | M54: 0 | N54: 200 | O54: 3800 | P54: -6885 | R54: 0 | T54: 53085
A55: 54 | B55: Henil Shah | D55: 278 | E55: 22 | F55: 22 | G55: 0 | H55: 0 | I55: 50000 | J55: Employee | K55: 3600 | L55: 0 | M55: 0 | N55: 200 | O55: 3800 | R55: 0 | T55: 46200
A56: 55 | B56: Hetal Arunbhai Agravat | D56: 3 | E56: 22 | F56: 22 | G56: 1.5 | H56: 0 | I56: 50000 | J56: Employee | K56: 3600 | L56: 0 | M56: 0 | N56: 200 | O56: 3800 | R56: 0 | T56: 46200
A57: 56 | B57: HETAL BHATT | E57: 22 | F57: 22 | G57: 0 | H57: 0 | I57: 50000 | J57: Employee | K57: 0 | L57: 0 | M57: 0 | N57: 200 | O57: 200 | R57: 0 | T57: 49800
A58: 57 | B58: Himshree Himanshu Dave | D58: 152 | E58: 22 | F58: 22 | G58: 0 | H58: 0 | I58: 50000 | J58: Employee | K58: 3600 | L58: 0 | M58: 0 | N58: 200 | O58: 3800 | R58: 0 | T58: 46200
A59: 58 | B59: Jaldhi Mahendrabhai Darji | D59: 76 | E59: 22 | F59: 22 | G59: 0 | H59: 0 | I59: 50000 | J59: Employee | K59: 0 | L59: 0 | M59: 0 | N59: 200 | O59: 200 | R59: 0 | T59: 49800
A60: 59 | B60: Jayeshkumar Ramchandra Khatri | D60: 130 | E60: 22 | F60: 22 | G60: 0 | H60: 0 | I60: 50000 | J60: Employee | K60: 0 | L60: 0 | M60: 0 | N60: 200 | O60: 200 | R60: 0 | T60: 49800
A61: 60 | B61: Jigar Ashokkumar Mehta | C61: Freelancer | E61: 22 | F61: 22 | G61: 0 | H61: 0 | I61: 50000 | J61: Consultant | K61: 0 | L61: 0 | M61: 0 | N61: 0 | O61: 0 | R61: 500 | T61: 49500
A62: 61 | B62: Jigar Deepak Bhinde | C62: Resigned on 24th Feb-Salary on Hold | D62: 133 | E62: 22 | F62: 22 | G62: 0 | H62: 0 | I62: 50000 | J62: Employee | K62: 3600 | L62: 0 | M62: 0 | N62: 200 | O62: 3800 | P62: 6000 | R62: 0 | T62: 40200
A63: 62 | B63: Jignesh Joshi | C63: DOJ 15th Mar | D63: 307 | E63: 22 | F63: 13 | G63: 10 | H63: 9 | I63: 9090.9091 | J63: Employee | K63: 0 | L63: 0 | M63: 0 | N63: 200 | O63: 200 | R63: 0 | T63: 8891
A64: 63 | B64: JIGNESH SHAH | D64: 132 | E64: 22 | F64: 22 | G64: 0 | H64: 0 | I64: 50000 | J64: Employee | K64: 0 | L64: 0 | M64: 0 | N64: 200 | O64: 200 | R64: 0 | T64: 49800
A65: 64 | B65: Jignesha Parmar | C65: Parttime Consultant | E65: 22 | F65: 22 | G65: 4 | H65: 0 | I65: 50000 | J65: Consultant | K65: 0 | L65: 0 | M65: 0 | N65: 0 | O65: 0 | R65: 5000 | T65: 45000
A66: 65 | B66: Kalpesh NaginBhai Patel | D66: 51 | E66: 22 | F66: 22 | G66: 1 | H66: 0 | I66: 50000 | J66: Employee | K66: 0 | L66: 0 | M66: 0 | N66: 200 | O66: 200 | R66: 7749 | T66: 42051
A67: 66 | B67: Kapil Thakar | D67: 267 | E67: 22 | F67: 22 | G67: 1 | H67: 0 | I67: 50000 | J67: Employee | K67: 0 | L67: 0 | M67: 0 | N67: 200 | O67: 200 | R67: 0 | T67: 49800
A68: 67 | B68: Kaushal BharatBhai Jayswal | D68: 101 | E68: 22 | F68: 22 | G68: 0 | H68: 0 | I68: 50000 | J68: Employee | K68: 0 | L68: 0 | M68: 0 | N68: 200 | O68: 200 | Q68: 4577 | R68: 0 | T68: 54377
A69: 68 | B69: Kaushalkumar Hirabhai Parmar | C69: Parttime Consultant | E69: 22 | F69: 22 | G69: 0 | H69: 0 | I69: 50000 | J69: Consultant | K69: 0 | L69: 0 | M69: 0 | N69: 0 | O69: 0 | R69: 500 | T69: 49500
A70: 69 | B70: Keta Thakkar | C70: Salary Already Paid | E70: 22 | F70: 22 | G70: 0 | H70: 0 | I70: 50000 | J70: Employee | K70: 0 | L70: 0 | M70: 0 | N70: 200 | O70: 200 | R70: 0 | T70: 49800
A71: 70 | B71: Ketan Mansukhbhai Ravat | D71: 129 | E71: 22 | F71: 22 | G71: 0 | H71: 0 | I71: 50000 | J71: Employee | K71: 0 | L71: 0 | M71: 0 | N71: 200 | O71: 200 | P71: 20833 | R71: 15980 | T71: 12987
A72: 71 | B72: Khushbu Maniyar | C72: Salary Already Paid | E72: 22 | F72: 22 | G72: 0 | H72: 0 | I72: 50000 | J72: Employee | K72: 0 | L72: 0 | M72: 0 | N72: 200 | O72: 200 | R72: 0 | T72: 49800
A73: 72 | B73: Kinjal Bipinbhai Hingu | D73: 50 | E73: 22 | F73: 22 | G73: 0 | H73: 0 | I73: 50000 | J73: Employee | K73: 3600 | L73: 0 | M73: 0 | N73: 200 | O73: 3800 | R73: 0 | T73: 46200
A74: 73 | B74: Kinjan Leela Jain | D74: 77 | E74: 22 | F74: 22 | G74: 0.5 | H74: 0 | I74: 50000 | J74: Employee | K74: 0 | L74: 0 | M74: 0 | N74: 200 | O74: 200 | R74: 10626 | T74: 39174
A75: 74 | B75: KOMAL TUNDIYA | E75: 22 | F75: 11 | G75: 0 | H75: 0 | I75: 25000 | J75: Employee | K75: 0 | L75: 0 | M75: 0 | N75: 200 | O75: 200 | R75: 0 | S75: 400 | T75: 24400
A76: 75 | B76: Krunal Lunagariya | D76: 245 | E76: 22 | F76: 22 | G76: 0 | H76: 0 | I76: 50000 | J76: Employee | K76: 3600 | L76: 0 | M76: 0 | N76: 200 | O76: 3800 | R76: 13063 | T76: 33137
A77: 76 | B77: KRUTI MANISHKUMAR BAGADIA | C77: Salary Already Paid | E77: 22 | F77: 22 | G77: 0 | H77: 0 | I77: 50000 | J77: Employee | K77: 0 | L77: 0 | M77: 0 | N77: 200 | O77: 200 | R77: 0 | T77: 49800
A78: 77 | B78: Kruttika Patel | D78: 285 | E78: 22 | F78: 22 | G78: 1 | H78: 0 | I78: 50000 | J78: Employee | K78: 0 | L78: 0 | M78: 0 | N78: 200 | O78: 200 | R78: 0 | T78: 49800
A79: 78 | B79: Kunal M Bhavsar | D79: 179 | E79: 22 | F79: 22 | G79: 0 | H79: 0 | I79: 50000 | J79: Employee | K79: 0 | L79: 0 | M79: 0 | N79: 200 | O79: 200 | R79: 13759 | T79: 36041
A80: 79 | B80: Kush Kiritkumar Jadia | D80: 25 | E80: 22 | F80: 22 | G80: 0 | H80: 0 | I80: 50000 | J80: Employee | K80: 3600 | L80: 0 | M80: 0 | N80: 200 | O80: 3800 | R80: 6155 | T80: 40045
A81: 80 | B81: Maharshi Gohel | C81: Resigned on 20th Feb-Salary on Hold | E81: 22 | F81: 22 | G81: 2 | H81: 2 | I81: 45454.545 | J81: Employee | K81: 3600 | L81: 0 | M81: 0 | N81: 200 | O81: 3800 | R81: 0 | T81: 41655
A82: 81 | B82: Manish Ambadas Patil | D82: 147 | E82: 22 | F82: 22 | G82: 1 | H82: 0 | I82: 50000 | J82: Employee | K82: 3600 | L82: 0 | M82: 0 | N82: 200 | O82: 3800 | R82: 2010 | T82: 44190
A83: 82 | B83: MANISHA MAKHIYAVIYA | C83: Salary Already Paid | E83: 22 | F83: 22 | G83: 0 | H83: 0 | I83: 50000 | J83: Employee | K83: 0 | L83: 0 | M83: 0 | N83: 200 | O83: 200 | R83: 0 | T83: 49800
A84: 83 | B84: Mansi Shaileshbhai Kakkad | D84: 85 | E84: 22 | F84: 22 | G84: 0.5 | H84: 0 | I84: 50000 | J84: Employee | K84: 0 | L84: 0 | M84: 0 | N84: 200 | O84: 200 | R84: 15697 | T84: 34103
A85: 84 | B85: Mayur Vinod kumar Jain | D85: 118 | E85: 22 | F85: 22 | G85: 0 | H85: 0 | I85: 50000 | J85: Employee | K85: 0 | L85: 0 | M85: 0 | N85: 200 | O85: 200 | P85: 40000 | R85: 6210 | T85: 3590
A86: 85 | B86: Mehul Girishbhai Rathod | D86: 222 | E86: 22 | F86: 22 | G86: 0 | H86: 0 | I86: 50000 | J86: Employee | K86: 0 | L86: 0 | M86: 0 | N86: 200 | O86: 200 | R86: 0 | T86: 49800
A87: 86 | B87: MehulKumar JayeshKumar Patel | D87: 104 | E87: 22 | F87: 22 | G87: 0 | H87: 0 | I87: 50000 | J87: Employee | K87: 0 | L87: 0 | M87: 2500 | N87: 200 | O87: 2700 | R87: 1074 | T87: 46226
A88: 87 | B88: Miten Soni | C88: DOJ 15th Mar | D88: 308 | E88: 22 | F88: 13 | G88: 0 | H88: 0 | I88: 29545.455 | J88: Employee | K88: 3600 | L88: 1181.8182 | M88: 0 | N88: 0 | O88: 4781.8182 | R88: 0 | T88: 24764
A89: 88 | B89: Mittalben Shah | C89: Salary Already Paid | E89: 22 | F89: 22 | G89: 0 | H89: 0 | I89: 50000 | J89: Employee | K89: 0 | L89: 0 | M89: 0 | N89: 200 | O89: 200 | R89: 0 | T89: 49800
A90: 89 | B90: Modi Vandana Hiteshbhai | D90: 146 | E90: 22 | F90: 22 | G90: 1 | H90: 0 | I90: 50000 | J90: Employee | K90: 3600 | L90: 0 | M90: 0 | N90: 200 | O90: 3800 | R90: 0 | T90: 46200
A91: 90 | B91: Mohit Solanki | D91: 291 | E91: 22 | F91: 22 | G91: 0 | H91: 0 | I91: 50000 | J91: Employee | K91: 0 | L91: 0 | M91: 0 | N91: 200 | O91: 200 | R91: 0 | T91: 49800
A92: 91 | B92: Moin Qureshi | D92: 293 | E92: 22 | F92: 22 | G92: 0 | H92: 0 | I92: 50000 | J92: Employee | K92: 3600 | L92: 0 | M92: 0 | N92: 200 | O92: 3800 | R92: 0 | T92: 46200
A93: 92 | B93: Mudit Meghraj Parakh | D93: 43 | E93: 22 | F93: 22 | G93: 2 | H93: 0 | I93: 50000 | J93: Employee | K93: 3600 | L93: 0 | M93: 0 | N93: 200 | O93: 3800 | R93: 6168 | T93: 40032
A94: 93 | B94: Nensi Dhingani | C94: Resigned-50%Salary on Hold- | D94: 121 | E94: 22 | F94: 22 | G94: 0 | H94: 0 | I94: 50000 | J94: Employee | K94: 0 | L94: 0 | M94: 0 | N94: 200 | O94: 200 | R94: 29470 | S94: 70833 | T94: -50503
A95: 94 | B95: Nikunj Joshi | C95: DOJ 1st Mar | D95: 302 | E95: 22 | F95: 22 | G95: 0 | H95: 0 | I95: 50000 | J95: Employee | K95: 3600 | L95: 0 | M95: 0 | N95: 200 | O95: 3800 | R95: 34111 | T95: 12089
A96: 95 | B96: Nilesh Dhirajlal Thakkar | D96: 168 | E96: 22 | F96: 22 | G96: 2 | H96: 0 | I96: 50000 | J96: Employee | K96: 0 | L96: 0 | M96: 0 | N96: 200 | O96: 200 | R96: 5980 | T96: 43820
A97: 96 | B97: Nirali Hirenkumar Joshi | D97: 182 | E97: 22 | F97: 22 | G97: 2 | H97: 0 | I97: 50000 | J97: Employee | K97: 3600 | L97: 0 | M97: 0 | N97: 200 | O97: 3800 | R97: 0 | T97: 46200
A98: 97 | B98: Nirmaben Samani | C98: Already paid on 9th Jan | E98: 22 | F98: 22 | G98: 0 | H98: 0 | I98: 50000 | J98: Employee | K98: 0 | L98: 0 | M98: 0 | N98: 200 | O98: 200 | P98: 49800 | R98: 0 | T98: 0
A99: 98 | B99: Nishant Nitin Gajjar | D99: 95 | E99: 22 | F99: 22 | G99: 1 | H99: 0 | I99: 50000 | J99: Employee | K99: 0 | L99: 0 | M99: 0 | N99: 200 | O99: 200 | R99: 0 | T99: 49800
A100: 99 | B100: Nitin Tribhovan Makwana | D100: 45 | E100: 22 | F100: 22 | G100: 3 | H100: 0 | I100: 50000 | J100: Employee | K100: 3600 | L100: 0 | M100: 0 | N100: 200 | O100: 3800 | Q100: 21975 | R100: 10160 | T100: 58015
...

Sheet CR&DR
A1: Row Labels | B1: Sum of Balance
A2: CR | B2: 0.20257873
A3: DR | B3: 0.79742127
A4: Grand Total | B4: 1

Sheet SBI
A1: Sl. No. | B1: Date | C1: Month | D1: Description | E1: Chq / Ref number | F1: Amount | G1: Dr / Cr | H1: Balance | I1: Dr / Cr2
A2: 1 | B2: 45016 | C2: March | D2: FD PREMAT PROCEEDS: 7951700057 | E2: 7951700057TO | F2: 199307 | G2: CR | H2: 42939146 | I2: CR
A3: 2 | B3: 45015 | C3: March | D3: Sweep Trf From: 7951700057 | F3: 361074 | G3: CR | H3: 43300220 | I3: CR
A4: 3 | B4: 45015 | C4: March | D4: DOLLY SHAH | E4: FCM-2303313P87OZ | F4: 79983 | G4: DR | H4: 43380203 | I4: CR
A5: 4 | B5: 45015 | C5: March | D5: HR MANAGEMENT AND PROJECTS PVT LTD | E5: FCM-2303313P87OW | F5: 301939 | G5: DR | H5: 43078264 | I5: CR
A6: 5 | B6: 45015 | C6: March | D6: HR MANAGEMENT AND PROJECTS PVT LTD | E6: FCM-2303313P87OY | F6: 430740 | G6: DR | H6: 42647524 | I6: CR
A7: 6 | B7: 45015 | C7: March | D7: EMA HOSPITALITY SERVICE APPARTMENT | E7: FCM-2303313P87OX | F7: 76229 | G7: DR | H7: 42571295 | I7: CR
A8: 7 | B8: 45015 | C8: March | D8: FD PREMAT PROCEEDS: 7951700057 | E8: 7951700057TO | F8: 155170 | G8: CR | H8: 42416125 | I8: CR
A9: 8 | B9: 45015 | C9: March | D9: Sweep Trf From: 7951700057 | F9: 446588 | G9: CR | H9: 42862713 | I9: CR | L9: First | M9: Last | N9: Month | O9: Opening Balance | P9: Closing Balance
A10: 9 | B10: 45015 | C10: March | D10: PRIVA UMNAG THAKKAR | E10: FCM-2303303ODRL5 | F10: 15109 | G10: DR | H10: 42877822 | I10: DR | L10: 44927 | M10: 44957 | N10: =TEXT(M10,"mmmm") -> January | O10: =INDEX(Table_BankStatement_14[Balance],MATCH(DATEVALUE(TEXT(L10,"dd-mm-yyyy")),Table_BankStatement_14[Date],0))+Table1[[#This Row],[Opening Balance]] -> #N/A | P10: =INDEX(Table_BankStatement_14[Balance],MATCH(DATEVALUE(TEXT(Table16[[#This Row],[Last]],"dd-mm-yyyy")),Table_BankStatement_14[Date],0))+Table1[[#This Row],[Closing Balance]] -> #N/A
A11: 10 | B11: 45015 | C11: March | D11: PRASHANT THAKKAR | E11: FCM-2303303ODRL6 | F11: 55859 | G11: DR | H11: 42821963 | I11: DR | L11: 44958 | M11: 44985 | N11: =TEXT(M11,"mmmm") -> February | O11: =INDEX(Table_BankStatement_14[Balance],MATCH(DATEVALUE(TEXT(L11,"dd-mm-yyyy")),Table_BankStatement_14[Date],0))+Table1[[#This Row],[Opening Balance]] -> #N/A | P11: =INDEX(Table_BankStatement_14[Balance],MATCH(DATEVALUE(TEXT(Table16[[#This Row],[Last]],"dd-mm-yyyy")),Table_BankStatement_14[Date],0))+Table1[[#This Row],[Closing Balance]] -> #N/A
A12: 11 | B12: 45015 | C12: March | D12: PRASHANT THAKKAR HUF | E12: FCM-2303303ODRL4 | F12: 128867 | G12: DR | H12: 42693096 | I12: DR | L12: 44986 | M12: 45016 | N12: =TEXT(M12,"mmmm") -> March | O12: =INDEX(Table_BankStatement_14[Balance],MATCH(DATEVALUE(TEXT(L12,"dd-mm-yyyy")),Table_BankStatement_14[Date],0))+Table1[[#This Row],[Opening Balance]] -> 312297 | P12: =INDEX(Table_BankStatement_14[Balance],MATCH(DATEVALUE(TEXT(Table16[[#This Row],[Last]],"dd-mm-yyyy")),Table_BankStatement_14[Date],0))+Table1[[#This Row],[Closing Balance]] -> 64408719
A13: 12 | B13: 45015 | C13: March | D13: SAPNA DEVANG SHAH | E13: FCM-2303303ODL5I | F13: 90560 | G13: DR | H13: 42602536 | I13: DR | L13: 45017 | M13: 45046 | N13: =TEXT(M13,"mmmm") -> April | O13: =INDEX(Table_BankStatement_14[Balance],MATCH(DATEVALUE(TEXT(L13,"dd-mm-yyyy")),Table_BankStatement_14[Date],0))+Table1[[#This Row],[Opening Balance]] -> 64408719 | P13: =INDEX(Table_BankStatement_14[Balance],MATCH(DATEVALUE(TEXT(Table16[[#This Row],[Last]],"dd-mm-yyyy")),Table_BankStatement_14[Date],0))+Table1[[#This Row],[Closing Balance]] -> 4048117.5
A14: 13 | B14: 45015 | C14: March | D14: ANKITA DARSHAN DAMANI | E14: FCM-2303303ODL5J | F14: 224695 | G14: DR | H14: 42377841 | I14: DR | L14: 45047 | M14: 45077 | N14: =TEXT(M14,"mmmm") -> May | O14: =INDEX(Table_BankStatement_14[Balance],MATCH(DATEVALUE(TEXT(L14,"dd-mm-yyyy")),Table_BankStatement_14[Date],0))+Table1[[#This Row],[Opening Balance]] -> #N/A | P14: =INDEX(Table_BankStatement_14[Balance],MATCH(DATEVALUE(TEXT(Table16[[#This Row],[Last]],"dd-mm-yyyy")),Table_BankStatement_14[Date],0))+Table1[[#This Row],[Closing Balance]] -> #N/A | S14: Row Labels | T14: Sum of Opening Balance | U14: Sum of Closing Balance
A15: 14 | B15: 45015 | C15: March | D15: SHAH MITTALBEN | E15: FCM-2303303ODL5H | F15: 495621 | G15: DR | H15: 41882220 | I15: DR | L15: 45078 | M15: 45107 | N15: =TEXT(M15,"mmmm") -> June | O15: =INDEX(Table_BankStatement_14[Balance],MATCH(DATEVALUE(TEXT(L15,"dd-mm-yyyy")),Table_BankStatement_14[Date],0))+Table1[[#This Row],[Opening Balance]] -> #N/A | P15: =INDEX(Table_BankStatement_14[Balance],MATCH(DATEVALUE(TEXT(Table16[[#This Row],[Last]],"dd-mm-yyyy")),Table_BankStatement_14[Date],0))+Table1[[#This Row],[Closing Balance]] -> #N/A | S15: March | T15: 312297 | U15: 64408719
A16: 15 | B16: 45015 | C16: March | D16: DHRUVI BHAVIKKUMAR DAMANI | E16: FCM-2303303ODL5G | F16: 55323 | G16: DR | H16: 41826897 | I16: DR | L16: 45108 | M16: 45138 | N16: =TEXT(M16,"mmmm") -> July | O16: =INDEX(Table_BankStatement_14[Balance],MATCH(DATEVALUE(TEXT(L16,"dd-mm-yyyy")),Table_BankStatement_14[Date],0))+Table1[[#This Row],[Opening Balance]] -> #N/A | P16: =INDEX(Table_BankStatement_14[Balance],MATCH(DATEVALUE(TEXT(Table16[[#This Row],[Last]],"dd-mm-yyyy")),Table_BankStatement_14[Date],0))+Table1[[#This Row],[Closing Balance]] -> #N/A
A17: 16 | B17: 45015 | C17: March | D17: MANIYAR KHUSHBOO DHAVALKUMAR | E17: FCM-2303303ODL5F | F17: 249001 | G17: DR | H17: 41577896 | I17: DR | L17: 45139 | M17: 45169 | N17: =TEXT(M17,"mmmm") -> August | O17: =INDEX(Table_BankStatement_14[Balance],MATCH(DATEVALUE(TEXT(L17,"dd-mm-yyyy")),Table_BankStatement_14[Date],0))+Table1[[#This Row],[Opening Balance]] -> #N/A | P17: =INDEX(Table_BankStatement_14[Balance],MATCH(DATEVALUE(TEXT(Table16[[#This Row],[Last]],"dd-mm-yyyy")),Table_BankStatement_14[Date],0))+Table1[[#This Row],[Closing Balance]] -> #N/A
A18: 17 | B18: 45015 | C18: March | D18: KETA UMANGKUMAR THAKKAR | E18: FCM-2303303ODL5E | F18: 46373 | G18: DR | H18: 41531523 | I18: DR | L18: 45170 | M18: 45199 | N18: =TEXT(M18,"mmmm") -> September | O18: =INDEX(Table_BankStatement_14[Balance],MATCH(DATEVALUE(TEXT(L18,"dd-mm-yyyy")),Table_BankStatement_14[Date],0))+Table1[[#This Row],[Opening Balance]] -> #N/A | P18: =INDEX(Table_BankStatement_14[Balance],MATCH(DATEVALUE(TEXT(Table16[[#This Row],[Last]],"dd-mm-yyyy")),Table_BankStatement_14[Date],0))+Table1[[#This Row],[Closing Balance]] -> #N/A
A19: 18 | B19: 45015 | C19: March | D19: ARTI CHINTAN KOTHARI | E19: FCM-2303303ODRPT | F19: 351996 | G19: DR | H19: 41179527 | I19: DR | L19: 45200 | M19: 45230 | N19: =TEXT(M19,"mmmm") -> October | O19: =INDEX(Table_BankStatement_14[Balance],MATCH(DATEVALUE(TEXT(L19,"dd-mm-yyyy")),Table_BankStatement_14[Date],0))+Table1[[#This Row],[Opening Balance]] -> #N/A | P19: =INDEX(Table_BankStatement_14[Balance],MATCH(DATEVALUE(TEXT(Table16[[#This Row],[Last]],"dd-mm-yyyy")),Table_BankStatement_14[Date],0))+Table1[[#This Row],[Closing Balance]] -> #N/A
A20: 19 | B20: 45015 | C20: March | D20: KESHAV RAJKUMAR AGARWAL | E20: FCM-2303303ODRPY | F20: 473570 | G20: DR | H20: 40705957 | I20: DR | L20: 45231 | M20: 45260 | N20: =TEXT(M20,"mmmm") -> November | O20: =INDEX(Table_BankStatement_14[Balance],MATCH(DATEVALUE(TEXT(L20,"dd-mm-yyyy")),Table_BankStatement_14[Date],0))+Table1[[#This Row],[Opening Balance]] -> #N/A | P20: =INDEX(Table_BankStatement_14[Balance],MATCH(DATEVALUE(TEXT(Table16[[#This Row],[Last]],"dd-mm-yyyy")),Table_BankStatement_14[Date],0))+Table1[[#This Row],[Closing Balance]] -> #N/A
A21: 20 | B21: 45015 | C21: March | D21: DISHA NIKHIL SANANDIYA | E21: FCM-2303303ODRPU | F21: 334761 | G21: DR | H21: 40371196 | I21: CR | L21: 45261 | M21: 45291 | N21: =TEXT(M21,"mmmm") -> December | O21: =INDEX(Table_BankStatement_14[Balance],MATCH(DATEVALUE(TEXT(L21,"dd-mm-yyyy")),Table_BankStatement_14[Date],0))+Table1[[#This Row],[Opening Balance]] -> #N/A | P21: =INDEX(Table_BankStatement_14[Balance],MATCH(DATEVALUE(TEXT(Table16[[#This Row],[Last]],"dd-mm-yyyy")),Table_BankStatement_14[Date],0))+Table1[[#This Row],[Closing Balance]] -> #N/A
A22: 21 | B22: 45015 | C22: March | D22: KRUTI MANISHKUMAR BAGADIA | E22: FCM-2303303ODRPW | F22: 211697 | G22: DR | H22: 40159499 | I22: CR
A23: 22 | B23: 45015 | C23: March | D23: S N D J CONSULTANTS PVT LTD | E23: FCM-2303303ODRPS | F23: 20245 | G23: DR | H23: 40139254 | I23: CR
A24: 23 | B24: 45015 | C24: March | D24: MANISHA MAKHIYAVIYA | E24: FCM-2303303ODRPV | F24: 244094 | G24: DR | H24: 39895160 | I24: CR
A25: 24 | B25: 45015 | C25: March | D25: BHARTIBEN TUSHARKUMAR ITALIYA | E25: FCM-2303303ODRPX | F25: 107121 | G25: DR | H25: 39788039 | I25: CR
A26: 25 | B26: 45013 | C26: March | D26: Sweep Trf From: 7951700057 | F26: 124901 | G26: CR | H26: 39663138 | I26: CR
A27: 26 | B27: 45013 | C27: March | D27: PG CREDIT CARD KOTAKCARD | E27: KPG-0185860263 | F27: 440765 | G27: DR | H27: 40103903 | I27: CR
A28: 27 | B28: 45012 | C28: March | D28: Sweep Trf From: 7951700057 | F28: 97275 | G28: CR | H28: 40006628 | I28: CR
A29: 28 | B29: 45012 | C29: March | D29: NEFT-EVERGREEN CORPORATE -CMS0862348056537 | E29: FCM-2303273N39MU | F29: 497243 | G29: DR | H29: 40503871 | I29: CR
A30: 29 | B30: 45009 | C30: March | D30: Sweep Trf From: 7951700057 | F30: 91960 | G30: CR | H30: 40411911 | I30: CR
A31: 30 | B31: 45009 | C31: March | D31: NEFT-AVION CLOUD SOLUTION-CMS0832347793565 | E31: FCM-2303233M3KOS | F31: 441758 | G31: DR | H31: 40853669 | I31: CR
A32: 31 | B32: 45008 | C32: March | D32: SWEEP TRANSFER TO [7951700057] | F32: 42782 | G32: DR | H32: 40810887 | I32: CR
A33: 32 | B33: 45008 | C33: March | D33: MB:SENT TO KMBL- COLLECTION ACCOUNT- NPS -NPS TRU | E33: MB-998923096053 | F33: 34136 | G33: DR | H33: 40776751 | I33: CR
A34: 33 | B34: 45008 | C34: March | D34: 2587MIS231161949 CRE001 GENOME MEDICAL INC | E34: TIP-b29881d1-492c-45 | F34: 140985 | G34: CR | H34: 40635766 | I34: CR
A35: 34 | B35: 45008 | C35: March | D35: 2587MIS231161949 CRE001 FCC-GOODS AND SERVICES TA | E35: TIP-b29881d1-492c-45 | F35: 89801 | G35: DR | H35: 40725567 | I35: CR
A36: 35 | B36: 45008 | C36: March | D36: 2587MIS231161916 CRE001 FCC-GOODS AND SERVICES TA | E36: TIP-3348372f-3fc5-4b | F36: 330991 | G36: DR | H36: 40394576 | I36: CR
A37: 36 | B37: 45008 | C37: March | D37: 2587MIS231161916 CRE001 EGALVANIC LLC | E37: TIP-3348372f-3fc5-4b | F37: 21530 | G37: CR | H37: 40373046 | I37: CR
A38: 37 | B38: 45008 | C38: March | D38: NEFT NRE REM INTELLIANTE INC BRENTDAVIDHOLLAND C | E38: NEFTINW-0561877713 | F38: 208207 | G38: CR | H38: 40581253 | I38: CR
A39: 38 | B39: 45007 | C39: March | D39: SWEEP TRANSFER TO [7951677370] | F39: 217891 | G39: DR | H39: 40799144 | I39: CR
A40: 39 | B40: 45007 | C40: March | D40: MB:RECEIVED FROM PANCHAL VISHAL ARVINDBHAI/INSTALL | E40: MB-998923876213 | F40: 361138 | G40: CR | H40: 40438006 | I40: CR
A41: 40 | B41: 45005 | C41: March | D41: SWEEP TRANSFER TO [7951630933] | F41: 354756 | G41: DR | H41: 40792762 | I41: CR
A42: 41 | B42: 45005 | C42: March | D42: NEFT MAHBH23079074410 IFM ENGINEERING PRIVATE LIM | E42: NEFTINW-0560472935 | F42: 143395 | G42: CR | H42: 40649367 | I42: CR
A43: 42 | B43: 45005 | C43: March | D43: PARESH DEVATVAL | E43: FCM-2303203L3XPJ | F43: 496983 | G43: DR | H43: 41146350 | I43: CR
A44: 43 | B44: 45005 | C44: March | D44: SHAH MANEK AND CO | E44: FCM-2303203L3XPK | F44: 207949 | G44: DR | H44: 40938401 | I44: CR
A45: 44 | B45: 45003 | C45: March | D45: Sweep Trf From: 7951572121 | F45: 399431 | G45: CR | H45: 40538970 | I45: CR
A46: 45 | B46: 45003 | C46: March | D46: HETAL HITESH BHATT | E46: FCM-2303183KN8OI | F46: 76267 | G46: DR | H46: 40615237 | I46: DR
A47: 46 | B47: 45003 | C47: March | D47: BHATT HITESH R | E47: FCM-2303183KN8OH | F47: 44850 | G47: DR | H47: 40570387 | I47: DR
A48: 47 | B48: 45003 | C48: March | D48: RAVINDRA CHUNILAL BHATT | E48: FCM-2303183KNFKK | F48: 70041 | G48: DR | H48: 40500346 | I48: CR
A49: 48 | B49: 45003 | C49: March | D49: IB: ETAX GSTN 0024535125 | E49: GBM-0024535125 | F49: 420886 | G49: DR | H49: 40079460 | I49: CR
A50: 49 | B50: 45003 | C50: March | D50: MB:BILLPAY FOR HDFCCARD 0412308625 | E50: EBPP-0412308625 | F50: 147383 | G50: DR | H50: 39932077 | I50: CR
A51: 50 | B51: 45002 | C51: March | D51: SWEEP TRANSFER TO [7951572121] | F51: 271837 | G51: DR | H51: 39660240 | I51: CR
A52: 51 | B52: 45002 | C52: March | D52: RTGS CHASR52023031700314971 BLITZZ INC CHAS0IN | E52: RTGSINW-0058617314 | F52: 376903 | G52: CR | H52: 39283337 | I52: CR
A53: 52 | B53: 45001 | C53: March | D53: FD PREMAT PROCEEDS: 7949648227 | E53: 7949648227TO | F53: 420189 | G53: CR | H53: 39703526 | I53: CR
A54: 53 | B54: 45001 | C54: March | D54: FD PREMAT PROCEEDS: 7950121018 | E54: 7950121018TO | F54: 241650 | G54: CR | H54: 39945176 | I54: CR
A55: 54 | B55: 45001 | C55: March | D55: FD PREMAT PROCEEDS: 7950188498 | E55: 7950188498TO | F55: 104361 | G55: CR | H55: 40049537 | I55: CR
A56: 55 | B56: 45001 | C56: March | D56: Sweep Trf From: 7949648227 | F56: 120090 | G56: CR | H56: 40169627 | I56: CR
A57: 56 | B57: 45001 | C57: March | D57: Sweep Trf From: 7950121018 | F57: 366422 | G57: CR | H57: 40536049 | I57: DR
A58: 57 | B58: 45001 | C58: March | D58: Sweep Trf From: 7950188498 | F58: 85546 | G58: CR | H58: 40621595 | I58: DR
A59: 58 | B59: 45001 | C59: March | D59: Sweep Trf From: 7951523700 | F59: 388603 | G59: CR | H59: 41010198 | I59: DR
A60: 59 | B60: 45001 | C60: March | D60: NEFT NRE REM INTELLIANTE INC BRENTDAVIDHOLLAND C | E60: NEFTINW-0558240989 | F60: 193997 | G60: CR | H60: 41204195 | I60: DR
A61: 60 | B61: 45001 | C61: March | D61: RTGS-SSPL SBI-KKBKR22023031608109103 | E61: FCM-2303163JPUJ8 | F61: 346531 | G61: DR | H61: 41550726 | I61: DR
A62: 61 | B62: 45000 | C62: March | D62: SWEEP TRANSFER TO [7951523700] | F62: 89064 | G62: DR | H62: 41461662 | I62: CR
A63: 62 | B63: 45000 | C63: March | D63: SentIMPS307422583892SCULPTSOFT/SBINX6917/SSPL SBI | E63: IMPS-307422768342 | F63: 322907 | G63: DR | H63: 41138755 | I63: CR
A64: 63 | B64: 45000 | C64: March | D64: CASH WITHDRAWAL BY SELF AT BOPAL | E64: 24 | F64: 474117 | G64: DR | H64: 40664638 | I64: CR
A65: 64 | B65: 45000 | C65: March | D65: 2587MIS231145397 CRE001 NATIONWIDE MANAGEMENT SER | E65: TIP-d4ebc713-d186-43 | F65: 28649 | G65: CR | H65: 40635989 | I65: CR
A66: 65 | B66: 45000 | C66: March | D66: 2587MIS231145397 CRE001 FCC-GOODS AND SERVICES TA | E66: TIP-d4ebc713-d186-43 | F66: 82434 | G66: DR | H66: 40718423 | I66: CR
A67: 66 | B67: 45000 | C67: March | D67: FD MATURITY PROCEEDS :7947631718/15-03-23/SCULPTSO | E67: TO | F67: 159640 | G67: CR | H67: 40558783 | I67: CR
A68: 67 | B68: 44999 | C68: March | D68: FD PREMAT PROCEEDS: 7950188498 | E68: 7950188498TO | F68: 106973 | G68: CR | H68: 40665756 | I68: CR
A69: 68 | B69: 44999 | C69: March | D69: Sweep Trf From: 7950188498 | F69: 488035 | G69: CR | H69: 41153791 | I69: CR
A70: 69 | B70: 44999 | C70: March | D70: CMS CHARGES PAY SCULPT01 23031400MP07 | E70: 2303143J7VAG | F70: 142980 | G70: DR | H70: 41296771 | I70: CR
A71: 70 | B71: 44999 | C71: March | D71: CMS GST PAY SCULPT01 23031400MNZG | E71: 2303143J7TL8 | F71: 245318 | G71: DR | H71: 41051453 | I71: CR
A72: 71 | B72: 44999 | C72: March | D72: SentIMPS307321118011SCULPTSOFT/SBINX6917/IB SSPL | E72: IMPS-307321536572 | F72: 217964 | G72: DR | H72: 40833489 | I72: CR
A73: 72 | B73: 44999 | C73: March | D73: IMPS-SOFTCONN TECHNOLOGIES | E73: FCM-2303143J4YXL | F73: 452839 | G73: DR | H73: 40380650 | I73: CR
A74: 73 | B74: 44999 | C74: March | D74: IMPS-SOFTCONN TECHNOLOGIES | E74: FCM-2303143J5691 | F74: 478330 | G74: DR | H74: 39902320 | I74: CR
A75: 74 | B75: 44999 | C75: March | D75: MB:BILLPAY FOR AIRTELBROADBAND 0411496827 | E75: EBPP-0411496827 | F75: 194891 | G75: DR | H75: 39707429 | I75: CR
A76: 75 | B76: 44998 | C76: March | D76: FD PREMAT PROCEEDS: 7950188498 | E76: 7950188498TO | F76: 170071 | G76: CR | H76: 39537358 | I76: CR
A77: 76 | B77: 44998 | C77: March | D77: Sweep Trf From: 7950188498 | F77: 107933 | G77: CR | H77: 39645291 | I77: CR
A78: 77 | B78: 44998 | C78: March | D78: PG AWS AMAZON PAY INDIA PRI | E78: KPG-0184976502 | F78: 203940 | G78: DR | H78: 39849231 | I78: CR
A79: 78 | B79: 44997 | C79: March | D79: CMSM_TXNCHG_SCULPT01_FEB_23 | E79: CMS-152935047D | F79: 357958 | G79: DR | H79: 39491273 | I79: CR
A80: 79 | B80: 44997 | C80: March | D80: CMSM_TXNCHG_SCULPT01_FEB_23 | E80: CMS-152923136D | F80: 39549 | G80: DR | H80: 39451724 | I80: CR
A81: 80 | B81: 44995 | C81: March | D81: CMS GST PAY SCULPT01 23031000MGQE | E81: 2303103I5NOE | F81: 479785 | G81: DR | H81: 38971939 | I81: CR
A82: 81 | B82: 44995 | C82: March | D82: CMS CHARGES PAY SCULPT01 23031000MH2W | E82: 2303103I5N7B | F82: 199362 | G82: DR | H82: 38772577 | I82: CR
A83: 82 | B83: 44995 | C83: March | D83: Chrg: Debit Card Annual Fee 0284 for 2023 (Value Date:09/03/2023) | E83: TBMS-1135709563 | F83: 281563 | G83: DR | H83: 38491014 | I83: CR
A84: 83 | B84: 44995 | C84: March | D84: IMPS-PRIYANK PATEL | E84: FCM-2303093HMF25 | F84: 67102 | G84: DR | H84: 38423912 | I84: CR
A85: 84 | B85: 44994 | C85: March | D85: FD PREMAT PROCEEDS: 7950280100 | E85: 7950280100TO | F85: 111991 | G85: CR | H85: 38311921 | I85: CR
A86: 85 | B86: 44994 | C86: March | D86: FD PREMAT PROCEEDS: 7950188498 | E86: 7950188498TO | F86: 418229 | G86: CR | H86: 38730150 | I86: CR
A87: 86 | B87: 44994 | C87: March | D87: Sweep Trf From: 7950188498 | F87: 446533 | G87: CR | H87: 39176683 | I87: CR
A88: 87 | B88: 44994 | C88: March | D88: Sweep Trf From: 7950280100 | F88: 112495 | G88: CR | H88: 39289178 | I88: DR
A89: 88 | B89: 44994 | C89: March | D89: PCD/0973/Paytm_Ahmedabadmunicip/380001090323/16:25 | E89: 306810686904 | F89: 54635 | G89: DR | H89: 39343813 | I89: DR
A90: 89 | B90: 44994 | C90: March | D90: MB:SENT TO KMBL- COLLECTION ACCOUNT- NPS -NPS TRU | E90: MB-998931427104 | F90: 449385 | G90: DR | H90: 38894428 | I90: DR
A91: 90 | B91: 44994 | C91: March | D91: MEHULKUMAR J PATEL-23030906MVU0 | E91: FCM-2303093HDI68 | F91: 447181 | G91: DR | H91: 38447247 | I91: DR
A92: 91 | B92: 44994 | C92: March | D92: IB: ETAX BILL DESK PAYME 0024343574 | E92: GBM-0024343574 | F92: 357784 | G92: DR | H92: 38089463 | I92: DR
A93: 92 | B93: 44994 | C93: March | D93: IB: ETAX EPFONEW 0024343387 | E93: GBM-0024343387 | F93: 77871 | G93: DR | H93: 38011592 | I93: DR
A94: 93 | B94: 44994 | C94: March | D94: PATEL VED PARESHBHAI | E94: FCM-2303083H8TJ6 | F94: 66060 | G94: DR | H94: 37945532 | I94: DR
A95: 94 | B95: 44994 | C95: March | D95: RATHOD MEHUL GIRISHBHAI | E95: FCM-2303083H8TJ7 | F95: 301255 | G95: DR | H95: 37644277 | I95: DR
A96: 95 | B96: 44994 | C96: March | D96: PATEL ASHVIN NARENDRABHAI | E96: FCM-2303083H8TJ4 | F96: 390136 | G96: DR | H96: 37254141 | I96: DR
A97: 96 | B97: 44994 | C97: March | D97: PATEL RAJATKUMAR KIRTIBHAI | E97: FCM-2303083H8TJA | F97: 409495 | G97: DR | H97: 36844646 | I97: DR
A98: 97 | B98: 44994 | C98: March | D98: PRASHANT THAKKAR | E98: FCM-2303083H8TJ2 | F98: 427310 | G98: DR | H98: 36417336 | I98: DR
A99: 98 | B99: 44994 | C99: March | D99: RAHUL MANOJKUMAR PARIKH | E99: FCM-2303083H8TJ9 | F99: 17284 | G99: DR | H99: 36400052 | I99: DR
A100: 99 | B100: 44994 | C100: March | D100: PATTANI ANANDI | E100: FCM-2303083H8TJ5 | F100: 299459 | G100: DR | H100: 36100593 | I100: DR
...

Sheet Kotak
A1: Sl. No. | B1: Date | C1: Month | D1: Description | E1: Chq / Ref number | F1: Amount | G1: Dr / Cr | H1: Balance | I1: Dr / Cr2
A2: 1 | B2: 45016 | C2: March | D2: FD PREMAT PROCEEDS: 7951700057 | E2: 7951700057TO | F2: 199307 | G2: CR | H2: =Table_BankStatement_14[[#This Row],[Balance]]/2 -> 21469573 | I2: CR
A3: 2 | B3: 45015 | C3: March | D3: Sweep Trf From: 7951700057 | F3: 361074 | G3: CR | H3: =Table_BankStatement_14[[#This Row],[Balance]]/2 -> 21650110 | I3: CR
A4: 3 | B4: 45015 | C4: March | D4: DOLLY SHAH | E4: FCM-2303313P87OZ | F4: 79983 | G4: DR | H4: =Table_BankStatement_14[[#This Row],[Balance]]/2 -> 21690102 | I4: CR
A5: 4 | B5: 45015 | C5: March | D5: HR MANAGEMENT AND PROJECTS PVT LTD | E5: FCM-2303313P87OW | F5: 301939 | G5: DR | H5: =Table_BankStatement_14[[#This Row],[Balance]]/2 -> 21539132 | I5: CR
A6: 5 | B6: 45015 | C6: March | D6: HR MANAGEMENT AND PROJECTS PVT LTD | E6: FCM-2303313P87OY | F6: 430740 | G6: DR | H6: =Table_BankStatement_14[[#This Row],[Balance]]/2 -> 21323762 | I6: CR
A7: 6 | B7: 45015 | C7: March | D7: EMA HOSPITALITY SERVICE APPARTMENT | E7: FCM-2303313P87OX | F7: 76229 | G7: DR | H7: =Table_BankStatement_14[[#This Row],[Balance]]/2 -> 21285648 | I7: CR
A8: 7 | B8: 45015 | C8: March | D8: FD PREMAT PROCEEDS: 7951700057 | E8: 7951700057TO | F8: 155170 | G8: CR | H8: =Table_BankStatement_14[[#This Row],[Balance]]/2 -> 21208062 | I8: CR
A9: 8 | B9: 45015 | C9: March | D9: Sweep Trf From: 7951700057 | F9: 446588 | G9: CR | H9: =Table_BankStatement_14[[#This Row],[Balance]]/2 -> 21431356 | I9: CR | L9: First | M9: Last | N9: Month | O9: Opening Balance | P9: Closing Balance
A10: 9 | B10: 45015 | C10: March | D10: PRIVA UMNAG THAKKAR | E10: FCM-2303303ODRL5 | F10: 15109 | G10: DR | H10: =Table_BankStatement_14[[#This Row],[Balance]]/2 -> 21438911 | I10: DR | L10: 44927 | M10: 44957 | N10: =TEXT(M10,"mmmm") -> January | O10: =INDEX(Table_BankStatement_1[Balance],MATCH(DATEVALUE(TEXT(L10,"dd-mm-yyyy")),Table_BankStatement_1[Date],0)) -> #N/A | P10: =INDEX(Table_BankStatement_1[Balance],MATCH(DATEVALUE(TEXT(Table1[[#This Row],[Last]],"dd-mm-yyyy")),Table_BankStatement_1[Date],0)) -> #N/A
A11: 10 | B11: 45015 | C11: March | D11: PRASHANT THAKKAR | E11: FCM-2303303ODRL6 | F11: 55859 | G11: DR | H11: =Table_BankStatement_14[[#This Row],[Balance]]/2 -> 21410982 | I11: DR | L11: 44958 | M11: 44985 | N11: =TEXT(M11,"mmmm") -> February | O11: =INDEX(Table_BankStatement_1[Balance],MATCH(DATEVALUE(TEXT(L11,"dd-mm-yyyy")),Table_BankStatement_1[Date],0)) -> #N/A | P11: =INDEX(Table_BankStatement_1[Balance],MATCH(DATEVALUE(TEXT(Table1[[#This Row],[Last]],"dd-mm-yyyy")),Table_BankStatement_1[Date],0)) -> #N/A
A12: 11 | B12: 45015 | C12: March | D12: PRASHANT THAKKAR HUF | E12: FCM-2303303ODRL4 | F12: 128867 | G12: DR | H12: =Table_BankStatement_14[[#This Row],[Balance]]/2 -> 21346548 | I12: DR | L12: 44986 | M12: 45016 | N12: =TEXT(M12,"mmmm") -> March | O12: =INDEX(Table_BankStatement_1[Balance],MATCH(DATEVALUE(TEXT(L12,"dd-mm-yyyy")),Table_BankStatement_1[Date],0)) -> 104099 | P12: =INDEX(Table_BankStatement_1[Balance],MATCH(DATEVALUE(TEXT(Table1[[#This Row],[Last]],"dd-mm-yyyy")),Table_BankStatement_1[Date],0)) -> 21469573
A13: 12 | B13: 45015 | C13: March | D13: SAPNA DEVANG SHAH | E13: FCM-2303303ODL5I | F13: 90560 | G13: DR | H13: =Table_BankStatement_14[[#This Row],[Balance]]/2 -> 21301268 | I13: DR | L13: 45017 | M13: 45046 | N13: =TEXT(M13,"mmmm") -> April | O13: =INDEX(Table_BankStatement_1[Balance],MATCH(DATEVALUE(TEXT(L13,"dd-mm-yyyy")),Table_BankStatement_1[Date],0)) -> 21469573 | P13: =INDEX(Table_BankStatement_1[Balance],MATCH(DATEVALUE(TEXT(Table1[[#This Row],[Last]],"dd-mm-yyyy")),Table_BankStatement_1[Date],0)) -> 1349372.5 | R13: Row Labels | S13: Sum of Closing Balance | T13: Sum of Opening Balance
A14: 13 | B14: 45015 | C14: March | D14: ANKITA DARSHAN DAMANI | E14: FCM-2303303ODL5J | F14: 224695 | G14: DR | H14: =Table_BankStatement_14[[#This Row],[Balance]]/2 -> 21188920 | I14: DR | L14: 45047 | M14: 45077 | N14: =TEXT(M14,"mmmm") -> May | O14: =INDEX(Table_BankStatement_1[Balance],MATCH(DATEVALUE(TEXT(L14,"dd-mm-yyyy")),Table_BankStatement_1[Date],0)) -> #N/A | P14: =INDEX(Table_BankStatement_1[Balance],MATCH(DATEVALUE(TEXT(Table1[[#This Row],[Last]],"dd-mm-yyyy")),Table_BankStatement_1[Date],0)) -> #N/A | R14: April | S14: 1362017 | T14: 21469573
A15: 14 | B15: 45015 | C15: March | D15: SHAH MITTALBEN | E15: FCM-2303303ODL5H | F15: 495621 | G15: DR | H15: =Table_BankStatement_14[[#This Row],[Balance]]/2 -> 20941110 | I15: DR | L15: 45078 | M15: 45107 | N15: =TEXT(M15,"mmmm") -> June | O15: =INDEX(Table_BankStatement_1[Balance],MATCH(DATEVALUE(TEXT(L15,"dd-mm-yyyy")),Table_BankStatement_1[Date],0)) -> #N/A | P15: =INDEX(Table_BankStatement_1[Balance],MATCH(DATEVALUE(TEXT(Table1[[#This Row],[Last]],"dd-mm-yyyy")),Table_BankStatement_1[Date],0)) -> #N/A
A16: 15 | B16: 45015 | C16: March | D16: DHRUVI BHAVIKKUMAR DAMANI | E16: FCM-2303303ODL5G | F16: 55323 | G16: DR | H16: =Table_BankStatement_14[[#This Row],[Balance]]/2 -> 20913448 | I16: DR | L16: 45108 | M16: 45138 | N16: =TEXT(M16,"mmmm") -> July | O16: =INDEX(Table_BankStatement_1[Balance],MATCH(DATEVALUE(TEXT(L16,"dd-mm-yyyy")),Table_BankStatement_1[Date],0)) -> #N/A | P16: =INDEX(Table_BankStatement_1[Balance],MATCH(DATEVALUE(TEXT(Table1[[#This Row],[Last]],"dd-mm-yyyy")),Table_BankStatement_1[Date],0)) -> #N/A
A17: 16 | B17: 45015 | C17: March | D17: MANIYAR KHUSHBOO DHAVALKUMAR | E17: FCM-2303303ODL5F | F17: 249001 | G17: DR | H17: =Table_BankStatement_14[[#This Row],[Balance]]/2 -> 20788948 | I17: DR | L17: 45139 | M17: 45169 | N17: =TEXT(M17,"mmmm") -> August | O17: =INDEX(Table_BankStatement_1[Balance],MATCH(DATEVALUE(TEXT(L17,"dd-mm-yyyy")),Table_BankStatement_1[Date],0)) -> #N/A | P17: =INDEX(Table_BankStatement_1[Balance],MATCH(DATEVALUE(TEXT(Table1[[#This Row],[Last]],"dd-mm-yyyy")),Table_BankStatement_1[Date],0)) -> #N/A
A18: 17 | B18: 45015 | C18: March | D18: KETA UMANGKUMAR THAKKAR | E18: FCM-2303303ODL5E | F18: 46373 | G18: DR | H18: =Table_BankStatement_14[[#This Row],[Balance]]/2 -> 20765762 | I18: DR | L18: 45170 | M18: 45199 | N18: =TEXT(M18,"mmmm") -> September | O18: =INDEX(Table_BankStatement_1[Balance],MATCH(DATEVALUE(TEXT(L18,"dd-mm-yyyy")),Table_BankStatement_1[Date],0)) -> #N/A | P18: =INDEX(Table_BankStatement_1[Balance],MATCH(DATEVALUE(TEXT(Table1[[#This Row],[Last]],"dd-mm-yyyy")),Table_BankStatement_1[Date],0)) -> #N/A
A19: 18 | B19: 45015 | C19: March | D19: ARTI CHINTAN KOTHARI | E19: FCM-2303303ODRPT | F19: 351996 | G19: DR | H19: =Table_BankStatement_14[[#This Row],[Balance]]/2 -> 20589764 | I19: DR | L19: 45200 | M19: 45230 | N19: =TEXT(M19,"mmmm") -> October | O19: =INDEX(Table_BankStatement_1[Balance],MATCH(DATEVALUE(TEXT(L19,"dd-mm-yyyy")),Table_BankStatement_1[Date],0)) -> #N/A | P19: =INDEX(Table_BankStatement_1[Balance],MATCH(DATEVALUE(TEXT(Table1[[#This Row],[Last]],"dd-mm-yyyy")),Table_BankStatement_1[Date],0)) -> #N/A
A20: 19 | B20: 45015 | C20: March | D20: KESHAV RAJKUMAR AGARWAL | E20: FCM-2303303ODRPY | F20: 473570 | G20: DR | H20: =Table_BankStatement_14[[#This Row],[Balance]]/2 -> 20352978 | I20: DR | L20: 45231 | M20: 45260 | N20: =TEXT(M20,"mmmm") -> November | O20: =INDEX(Table_BankStatement_1[Balance],MATCH(DATEVALUE(TEXT(L20,"dd-mm-yyyy")),Table_BankStatement_1[Date],0)) -> #N/A | P20: =INDEX(Table_BankStatement_1[Balance],MATCH(DATEVALUE(TEXT(Table1[[#This Row],[Last]],"dd-mm-yyyy")),Table_BankStatement_1[Date],0)) -> #N/A
A21: 20 | B21: 45015 | C21: March | D21: DISHA NIKHIL SANANDIYA | E21: FCM-2303303ODRPU | F21: 334761 | G21: DR | H21: =Table_BankStatement_14[[#This Row],[Balance]]/2 -> 20185598 | I21: CR | L21: 45261 | M21: 45291 | N21: =TEXT(M21,"mmmm") -> December | O21: =INDEX(Table_BankStatement_1[Balance],MATCH(DATEVALUE(TEXT(L21,"dd-mm-yyyy")),Table_BankStatement_1[Date],0)) -> #N/A | P21: =INDEX(Table_BankStatement_1[Balance],MATCH(DATEVALUE(TEXT(Table1[[#This Row],[Last]],"dd-mm-yyyy")),Table_BankStatement_1[Date],0)) -> #N/A
A22: 21 | B22: 45015 | C22: March | D22: KRUTI MANISHKUMAR BAGADIA | E22: FCM-2303303ODRPW | F22: 211697 | G22: DR | H22: =Table_BankStatement_14[[#This Row],[Balance]]/2 -> 20079750 | I22: CR
A23: 22 | B23: 45015 | C23: March | D23: S N D J CONSULTANTS PVT LTD | E23: FCM-2303303ODRPS | F23: 20245 | G23: DR | H23: =Table_BankStatement_14[[#This Row],[Balance]]/2 -> 20069627 | I23: CR
A24: 23 | B24: 45015 | C24: March | D24: MANISHA MAKHIYAVIYA | E24: FCM-2303303ODRPV | F24: 244094 | G24: DR | H24: =Table_BankStatement_14[[#This Row],[Balance]]/2 -> 19947580 | I24: CR
A25: 24 | B25: 45015 | C25: March | D25: BHARTIBEN TUSHARKUMAR ITALIYA | E25: FCM-2303303ODRPX | F25: 107121 | G25: DR | H25: =Table_BankStatement_14[[#This Row],[Balance]]/2 -> 19894020 | I25: CR
A26: 25 | B26: 45013 | C26: March | D26: Sweep Trf From: 7951700057 | F26: 124901 | G26: CR | H26: =Table_BankStatement_14[[#This Row],[Balance]]/2 -> 19831569 | I26: CR
A27: 26 | B27: 45013 | C27: March | D27: PG CREDIT CARD KOTAKCARD | E27: KPG-0185860263 | F27: 440765 | G27: DR | H27: =Table_BankStatement_14[[#This Row],[Balance]]/2 -> 20051952 | I27: CR
A28: 27 | B28: 45012 | C28: March | D28: Sweep Trf From: 7951700057 | F28: 97275 | G28: CR | H28: =Table_BankStatement_14[[#This Row],[Balance]]/2 -> 20003314 | I28: CR
A29: 28 | B29: 45012 | C29: March | D29: NEFT-EVERGREEN CORPORATE -CMS0862348056537 | E29: FCM-2303273N39MU | F29: 497243 | G29: DR | H29: =Table_BankStatement_14[[#This Row],[Balance]]/2 -> 20251936 | I29: CR
A30: 29 | B30: 45009 | C30: March | D30: Sweep Trf From: 7951700057 | F30: 91960 | G30: CR | H30: =Table_BankStatement_14[[#This Row],[Balance]]/2 -> 20205956 | I30: CR
A31: 30 | B31: 45009 | C31: March | D31: NEFT-AVION CLOUD SOLUTION-CMS0832347793565 | E31: FCM-2303233M3KOS | F31: 441758 | G31: DR | H31: =Table_BankStatement_14[[#This Row],[Balance]]/2 -> 20426834 | I31: CR
A32: 31 | B32: 45008 | C32: March | D32: SWEEP TRANSFER TO [7951700057] | F32: 42782 | G32: DR | H32: =Table_BankStatement_14[[#This Row],[Balance]]/2 -> 20405444 | I32: CR
A33: 32 | B33: 45008 | C33: March | D33: MB:SENT TO KMBL- COLLECTION ACCOUNT- NPS -NPS TRU | E33: MB-998923096053 | F33: 34136 | G33: DR | H33: =Table_BankStatement_14[[#This Row],[Balance]]/2 -> 20388376 | I33: CR
A34: 33 | B34: 45008 | C34: March | D34: 2587MIS231161949 CRE001 GENOME MEDICAL INC | E34: TIP-b29881d1-492c-45 | F34: 140985 | G34: CR | H34: =Table_BankStatement_14[[#This Row],[Balance]]/2 -> 20317883 | I34: CR
A35: 34 | B35: 45008 | C35: March | D35: 2587MIS231161949 CRE001 FCC-GOODS AND SERVICES TA | E35: TIP-b29881d1-492c-45 | F35: 89801 | G35: DR | H35: =Table_BankStatement_14[[#This Row],[Balance]]/2 -> 20362784 | I35: CR
A36: 35 | B36: 45008 | C36: March | D36: 2587MIS231161916 CRE001 FCC-GOODS AND SERVICES TA | E36: TIP-3348372f-3fc5-4b | F36: 330991 | G36: DR | H36: =Table_BankStatement_14[[#This Row],[Balance]]/2 -> 20197288 | I36: CR
A37: 36 | B37: 45008 | C37: March | D37: 2587MIS231161916 CRE001 EGALVANIC LLC | E37: TIP-3348372f-3fc5-4b | F37: 21530 | G37: CR | H37: =Table_BankStatement_14[[#This Row],[Balance]]/2 -> 20186523 | I37: CR
A38: 37 | B38: 45008 | C38: March | D38: NEFT NRE REM INTELLIANTE INC BRENTDAVIDHOLLAND C | E38: NEFTINW-0561877713 | F38: 208207 | G38: CR | H38: =Table_BankStatement_14[[#This Row],[Balance]]/2 -> 20290626 | I38: CR
A39: 38 | B39: 45007 | C39: March | D39: SWEEP TRANSFER TO [7951677370] | F39: 217891 | G39: DR | H39: =Table_BankStatement_14[[#This Row],[Balance]]/2 -> 20399572 | I39: CR
A40: 39 | B40: 45007 | C40: March | D40: MB:RECEIVED FROM PANCHAL VISHAL ARVINDBHAI/INSTALL | E40: MB-998923876213 | F40: 361138 | G40: CR | H40: =Table_BankStatement_14[[#This Row],[Balance]]/2 -> 20219003 | I40: CR
A41: 40 | B41: 45005 | C41: March | D41: SWEEP TRANSFER TO [7951630933] | F41: 354756 | G41: DR | H41: =Table_BankStatement_14[[#This Row],[Balance]]/2 -> 20396381 | I41: CR
A42: 41 | B42: 45005 | C42: March | D42: NEFT MAHBH23079074410 IFM ENGINEERING PRIVATE LIM | E42: NEFTINW-0560472935 | F42: 143395 | G42: CR | H42: =Table_BankStatement_14[[#This Row],[Balance]]/2 -> 20324684 | I42: CR
A43: 42 | B43: 45005 | C43: March | D43: PARESH DEVATVAL | E43: FCM-2303203L3XPJ | F43: 496983 | G43: DR | H43: =Table_BankStatement_14[[#This Row],[Balance]]/2 -> 20573175 | I43: CR
A44: 43 | B44: 45005 | C44: March | D44: SHAH MANEK AND CO | E44: FCM-2303203L3XPK | F44: 207949 | G44: DR | H44: =Table_BankStatement_14[[#This Row],[Balance]]/2 -> 20469200 | I44: CR
A45: 44 | B45: 45003 | C45: March | D45: Sweep Trf From: 7951572121 | F45: 399431 | G45: CR | H45: =Table_BankStatement_14[[#This Row],[Balance]]/2 -> 20269485 | I45: CR
A46: 45 | B46: 45003 | C46: March | D46: HETAL HITESH BHATT | E46: FCM-2303183KN8OI | F46: 76267 | G46: DR | H46: =Table_BankStatement_14[[#This Row],[Balance]]/2 -> 20307618 | I46: DR
A47: 46 | B47: 45003 | C47: March | D47: BHATT HITESH R | E47: FCM-2303183KN8OH | F47: 44850 | G47: DR | H47: =Table_BankStatement_14[[#This Row],[Balance]]/2 -> 20285194 | I47: DR
A48: 47 | B48: 45003 | C48: March | D48: RAVINDRA CHUNILAL BHATT | E48: FCM-2303183KNFKK | F48: 70041 | G48: DR | H48: =Table_BankStatement_14[[#This Row],[Balance]]/2 -> 20250173 | I48: CR
A49: 48 | B49: 45003 | C49: March | D49: IB: ETAX GSTN 0024535125 | E49: GBM-0024535125 | F49: 420886 | G49: DR | H49: =Table_BankStatement_14[[#This Row],[Balance]]/2 -> 20039730 | I49: CR
A50: 49 | B50: 45003 | C50: March | D50: MB:BILLPAY FOR HDFCCARD 0412308625 | E50: EBPP-0412308625 | F50: 147383 | G50: DR | H50: =Table_BankStatement_14[[#This Row],[Balance]]/2 -> 19966038 | I50: CR
A51: 50 | B51: 45002 | C51: March | D51: SWEEP TRANSFER TO [7951572121] | F51: 271837 | G51: DR | H51: =Table_BankStatement_14[[#This Row],[Balance]]/2 -> 19830120 | I51: CR
A52: 51 | B52: 45002 | C52: March | D52: RTGS CHASR52023031700314971 BLITZZ INC CHAS0IN | E52: RTGSINW-0058617314 | F52: 376903 | G52: CR | H52: =Table_BankStatement_14[[#This Row],[Balance]]/2 -> 19641668 | I52: CR
A53: 52 | B53: 45001 | C53: March | D53: FD PREMAT PROCEEDS: 7949648227 | E53: 7949648227TO | F53: 420189 | G53: CR | H53: =Table_BankStatement_14[[#This Row],[Balance]]/2 -> 19851763 | I53: CR
A54: 53 | B54: 45001 | C54: March | D54: FD PREMAT PROCEEDS: 7950121018 | E54: 7950121018TO | F54: 241650 | G54: CR | H54: =Table_BankStatement_14[[#This Row],[Balance]]/2 -> 19972588 | I54: CR
A55: 54 | B55: 45001 | C55: March | D55: FD PREMAT PROCEEDS: 7950188498 | E55: 7950188498TO | F55: 104361 | G55: CR | H55: =Table_BankStatement_14[[#This Row],[Balance]]/2 -> 20024768 | I55: CR
A56: 55 | B56: 45001 | C56: March | D56: Sweep Trf From: 7949648227 | F56: 120090 | G56: CR | H56: =Table_BankStatement_14[[#This Row],[Balance]]/2 -> 20084814 | I56: CR
A57: 56 | B57: 45001 | C57: March | D57: Sweep Trf From: 7950121018 | F57: 366422 | G57: CR | H57: =Table_BankStatement_14[[#This Row],[Balance]]/2 -> 20268024 | I57: DR
A58: 57 | B58: 45001 | C58: March | D58: Sweep Trf From: 7950188498 | F58: 85546 | G58: CR | H58: =Table_BankStatement_14[[#This Row],[Balance]]/2 -> 20310798 | I58: DR
A59: 58 | B59: 45001 | C59: March | D59: Sweep Trf From: 7951523700 | F59: 388603 | G59: CR | H59: =Table_BankStatement_14[[#This Row],[Balance]]/2 -> 20505099 | I59: DR
A60: 59 | B60: 45001 | C60: March | D60: NEFT NRE REM INTELLIANTE INC BRENTDAVIDHOLLAND C | E60: NEFTINW-0558240989 | F60: 193997 | G60: CR | H60: =Table_BankStatement_14[[#This Row],[Balance]]/2 -> 20602098 | I60: DR
A61: 60 | B61: 45001 | C61: March | D61: RTGS-SSPL SBI-KKBKR22023031608109103 | E61: FCM-2303163JPUJ8 | F61: 346531 | G61: DR | H61: =Table_BankStatement_14[[#This Row],[Balance]]/2 -> 20775363 | I61: DR
A62: 61 | B62: 45000 | C62: March | D62: SWEEP TRANSFER TO [7951523700] | F62: 89064 | G62: DR | H62: =Table_BankStatement_14[[#This Row],[Balance]]/2 -> 20730831 | I62: CR
A63: 62 | B63: 45000 | C63: March | D63: SentIMPS307422583892SCULPTSOFT/SBINX6917/SSPL SBI | E63: IMPS-307422768342 | F63: 322907 | G63: DR | H63: =Table_BankStatement_14[[#This Row],[Balance]]/2 -> 20569378 | I63: CR
A64: 63 | B64: 45000 | C64: March | D64: CASH WITHDRAWAL BY SELF AT BOPAL | E64: 24 | F64: 474117 | G64: DR | H64: =Table_BankStatement_14[[#This Row],[Balance]]/2 -> 20332319 | I64: CR
A65: 64 | B65: 45000 | C65: March | D65: 2587MIS231145397 CRE001 NATIONWIDE MANAGEMENT SER | E65: TIP-d4ebc713-d186-43 | F65: 28649 | G65: CR | H65: =Table_BankStatement_14[[#This Row],[Balance]]/2 -> 20317994 | I65: CR
A66: 65 | B66: 45000 | C66: March | D66: 2587MIS231145397 CRE001 FCC-GOODS AND SERVICES TA | E66: TIP-d4ebc713-d186-43 | F66: 82434 | G66: DR | H66: =Table_BankStatement_14[[#This Row],[Balance]]/2 -> 20359212 | I66: CR
A67: 66 | B67: 45000 | C67: March | D67: FD MATURITY PROCEEDS :7947631718/15-03-23/SCULPTSO | E67: TO | F67: 159640 | G67: CR | H67: =Table_BankStatement_14[[#This Row],[Balance]]/2 -> 20279392 | I67: CR
A68: 67 | B68: 44999 | C68: March | D68: FD PREMAT PROCEEDS: 7950188498 | E68: 7950188498TO | F68: 106973 | G68: CR | H68: =Table_BankStatement_14[[#This Row],[Balance]]/2 -> 20332878 | I68: CR
A69: 68 | B69: 44999 | C69: March | D69: Sweep Trf From: 7950188498 | F69: 488035 | G69: CR | H69: =Table_BankStatement_14[[#This Row],[Balance]]/2 -> 20576896 | I69: CR
A70: 69 | B70: 44999 | C70: March | D70: CMS CHARGES PAY SCULPT01 23031400MP07 | E70: 2303143J7VAG | F70: 142980 | G70: DR | H70: =Table_BankStatement_14[[#This Row],[Balance]]/2 -> 20648386 | I70: CR
A71: 70 | B71: 44999 | C71: March | D71: CMS GST PAY SCULPT01 23031400MNZG | E71: 2303143J7TL8 | F71: 245318 | G71: DR | H71: =Table_BankStatement_14[[#This Row],[Balance]]/2 -> 20525726 | I71: CR
A72: 71 | B72: 44999 | C72: March | D72: SentIMPS307321118011SCULPTSOFT/SBINX6917/IB SSPL | E72: IMPS-307321536572 | F72: 217964 | G72: DR | H72: =Table_BankStatement_14[[#This Row],[Balance]]/2 -> 20416744 | I72: CR
A73: 72 | B73: 44999 | C73: March | D73: IMPS-SOFTCONN TECHNOLOGIES | E73: FCM-2303143J4YXL | F73: 452839 | G73: DR | H73: =Table_BankStatement_14[[#This Row],[Balance]]/2 -> 20190325 | I73: CR
A74: 73 | B74: 44999 | C74: March | D74: IMPS-SOFTCONN TECHNOLOGIES | E74: FCM-2303143J5691 | F74: 478330 | G74: DR | H74: =Table_BankStatement_14[[#This Row],[Balance]]/2 -> 19951160 | I74: CR
A75: 74 | B75: 44999 | C75: March | D75: MB:BILLPAY FOR AIRTELBROADBAND 0411496827 | E75: EBPP-0411496827 | F75: 194891 | G75: DR | H75: =Table_BankStatement_14[[#This Row],[Balance]]/2 -> 19853714 | I75: CR
A76: 75 | B76: 44998 | C76: March | D76: FD PREMAT PROCEEDS: 7950188498 | E76: 7950188498TO | F76: 170071 | G76: CR | H76: =Table_BankStatement_14[[#This Row],[Balance]]/2 -> 19768679 | I76: CR
A77: 76 | B77: 44998 | C77: March | D77: Sweep Trf From: 7950188498 | F77: 107933 | G77: CR | H77: =Table_BankStatement_14[[#This Row],[Balance]]/2 -> 19822646 | I77: CR
A78: 77 | B78: 44998 | C78: March | D78: PG AWS AMAZON PAY INDIA PRI | E78: KPG-0184976502 | F78: 203940 | G78: DR | H78: =Table_BankStatement_14[[#This Row],[Balance]]/2 -> 19924616 | I78: CR
A79: 78 | B79: 44997 | C79: March | D79: CMSM_TXNCHG_SCULPT01_FEB_23 | E79: CMS-152935047D | F79: 357958 | G79: DR | H79: =Table_BankStatement_14[[#This Row],[Balance]]/2 -> 19745636 | I79: CR
A80: 79 | B80: 44997 | C80: March | D80: CMSM_TXNCHG_SCULPT01_FEB_23 | E80: CMS-152923136D | F80: 39549 | G80: DR | H80: =Table_BankStatement_14[[#This Row],[Balance]]/2 -> 19725862 | I80: CR
A81: 80 | B81: 44995 | C81: March | D81: CMS GST PAY SCULPT01 23031000MGQE | E81: 2303103I5NOE | F81: 479785 | G81: DR | H81: =Table_BankStatement_14[[#This Row],[Balance]]/2 -> 19485970 | I81: CR
A82: 81 | B82: 44995 | C82: March | D82: CMS CHARGES PAY SCULPT01 23031000MH2W | E82: 2303103I5N7B | F82: 199362 | G82: DR | H82: =Table_BankStatement_14[[#This Row],[Balance]]/2 -> 19386288 | I82: CR
A83: 82 | B83: 44995 | C83: March | D83: Chrg: Debit Card Annual Fee 0284 for 2023 (Value Date:09/03/2023) | E83: TBMS-1135709563 | F83: 281563 | G83: DR | H83: =Table_BankStatement_14[[#This Row],[Balance]]/2 -> 19245507 | I83: CR
A84: 83 | B84: 44995 | C84: March | D84: IMPS-PRIYANK PATEL | E84: FCM-2303093HMF25 | F84: 67102 | G84: DR | H84: =Table_BankStatement_14[[#This Row],[Balance]]/2 -> 19211956 | I84: CR
A85: 84 | B85: 44994 | C85: March | D85: FD PREMAT PROCEEDS: 7950280100 | E85: 7950280100TO | F85: 111991 | G85: CR | H85: =Table_BankStatement_14[[#This Row],[Balance]]/2 -> 19155960 | I85: CR
A86: 85 | B86: 44994 | C86: March | D86: FD PREMAT PROCEEDS: 7950188498 | E86: 7950188498TO | F86: 418229 | G86: CR | H86: =Table_BankStatement_14[[#This Row],[Balance]]/2 -> 19365075 | I86: CR
A87: 86 | B87: 44994 | C87: March | D87: Sweep Trf From: 7950188498 | F87: 446533 | G87: CR | H87: =Table_BankStatement_14[[#This Row],[Balance]]/2 -> 19588342 | I87: CR
A88: 87 | B88: 44994 | C88: March | D88: Sweep Trf From: 7950280100 | F88: 112495 | G88: CR | H88: =Table_BankStatement_14[[#This Row],[Balance]]/2 -> 19644589 | I88: DR
A89: 88 | B89: 44994 | C89: March | D89: PCD/0973/Paytm_Ahmedabadmunicip/380001090323/16:25 | E89: 306810686904 | F89: 54635 | G89: DR | H89: =Table_BankStatement_14[[#This Row],[Balance]]/2 -> 19671906 | I89: DR
A90: 89 | B90: 44994 | C90: March | D90: MB:SENT TO KMBL- COLLECTION ACCOUNT- NPS -NPS TRU | E90: MB-998931427104 | F90: 449385 | G90: DR | H90: =Table_BankStatement_14[[#This Row],[Balance]]/2 -> 19447214 | I90: DR
A91: 90 | B91: 44994 | C91: March | D91: MEHULKUMAR J PATEL-23030906MVU0 | E91: FCM-2303093HDI68 | F91: 447181 | G91: DR | H91: =Table_BankStatement_14[[#This Row],[Balance]]/2 -> 19223624 | I91: DR
A92: 91 | B92: 44994 | C92: March | D92: IB: ETAX BILL DESK PAYME 0024343574 | E92: GBM-0024343574 | F92: 357784 | G92: DR | H92: =Table_BankStatement_14[[#This Row],[Balance]]/2 -> 19044732 | I92: DR
A93: 92 | B93: 44994 | C93: March | D93: IB: ETAX EPFONEW 0024343387 | E93: GBM-0024343387 | F93: 77871 | G93: DR | H93: =Table_BankStatement_14[[#This Row],[Balance]]/2 -> 19005796 | I93: DR
A94: 93 | B94: 44994 | C94: March | D94: PATEL VED PARESHBHAI | E94: FCM-2303083H8TJ6 | F94: 66060 | G94: DR | H94: =Table_BankStatement_14[[#This Row],[Balance]]/2 -> 18972766 | I94: DR
A95: 94 | B95: 44994 | C95: March | D95: RATHOD MEHUL GIRISHBHAI | E95: FCM-2303083H8TJ7 | F95: 301255 | G95: DR | H95: =Table_BankStatement_14[[#This Row],[Balance]]/2 -> 18822138 | I95: DR
A96: 95 | B96: 44994 | C96: March | D96: PATEL ASHVIN NARENDRABHAI | E96: FCM-2303083H8TJ4 | F96: 390136 | G96: DR | H96: =Table_BankStatement_14[[#This Row],[Balance]]/2 -> 18627070 | I96: DR
A97: 96 | B97: 44994 | C97: March | D97: PATEL RAJATKUMAR KIRTIBHAI | E97: FCM-2303083H8TJA | F97: 409495 | G97: DR | H97: =Table_BankStatement_14[[#This Row],[Balance]]/2 -> 18422323 | I97: DR
A98: 97 | B98: 44994 | C98: March | D98: PRASHANT THAKKAR | E98: FCM-2303083H8TJ2 | F98: 427310 | G98: DR | H98: =Table_BankStatement_14[[#This Row],[Balance]]/2 -> 18208668 | I98: DR
A99: 98 | B99: 44994 | C99: March | D99: RAHUL MANOJKUMAR PARIKH | E99: FCM-2303083H8TJ9 | F99: 17284 | G99: DR | H99: =Table_BankStatement_14[[#This Row],[Balance]]/2 -> 18200026 | I99: DR
A100: 99 | B100: 44994 | C100: March | D100: PATTANI ANANDI | E100: FCM-2303083H8TJ5 | F100: 299459 | G100: DR | H100: =Table_BankStatement_14[[#This Row],[Balance]]/2 -> 18050296 | I100: DR
...

Sheet FuzzyLookup_AddIn_Undo_Sheet
A1: Sr No | B1: Employee Code | C1: Column1 | D1: Employee name | E1: Manager Name RM1 | F1: Manager Name RM2 | G1: Table28.Project | H1: Salary to be Paid
A2: 1 | B2: 4 | D2: Bansi Jayantibhai Sojitra | E2: MehulKumar JayeshKumar Patel | F2: Mayur Vinod kumar Jain | G2: VSI-Nationwide | H2: 49800
A3: 49 | B3: 3 | D3: Hetal Arunbhai Agravat | E3: MehulKumar JayeshKumar Patel | F3: Mayur Vinod kumar Jain | G3: VSI-Nationwide | H3: 46200
A4: 2 | B4: 9 | D4: Dhananjay Rajeshbhai Dhobi | E4: Prashant Thakkar | F4: Prashant Thakkar | G4: IFM | H4: 9138
A5: 3 | B5: 18 | D5: Priyank Mahendrabhai Patel | E5: Prashant Thakkar | F5: Prashant Thakkar | G5: Blitzz | H5: -10374
A6: 4 | B6: 13 | D6: Vivek Ashvinbhai Joshi | E6: Prashant Thakkar | F6: Prashant Thakkar | G6: Risk AI/Genome | H6: 30556
A7: 5 | B7: 22 | D7: Binal Rajeshbhai Kharecha | E7: Anil Babubhai Variya | F7: Vishal Prajapati | G7: Blitzz | H7: 49800
A8: 6 | B8: 25 | D8: Kush Kiritkumar Jadia | E8: RITESH JAIN | F8: RITESH JAIN | G8: Vsite-RemoteVal | H8: 40045
A9: 7 | B9: 28 | D9: Vishal Arvindbhai Panchal | E9: Prashant Thakkar | F9: Prashant Thakkar | G9: Genome | H9: 32209
A10: 8 | B10: 38 | D10: Pankti Milap Patel | E10: Arpit Makhiyaviya | F10: Arpit Makhiyaviya | G10: Genome | H10: 24133
A11: 9 | B11: 42 | D11: Ashwin Narendrabhai Patel | E11: Vishal Prajapati | F11: Vishal Prajapati | G11: Blitzz | H11: 49800
A12: 10 | B12: 43 | D12: Mudit Meghraj Parakh | E12: Arpit Makhiyaviya | F12: Arpit Makhiyaviya | G12: Genome | H12: 40032
A13: 11 | B13: 45 | D13: Nitin Tribhovan Makwana | E13: Vishal Prajapati | F13: Vishal Prajapati | G13: Blitzz | H13: 58015
... A88: 107 | B88: 278 | D88: Henil Shah | E88: Ankit Prajapati | F88: Vivek Ashvinbhai Joshi | G88: Risk AI/Genome | H88: 46200
A89: 83 | B89: 290 | D89: Vedkumar Patel | E89: Vainik Kakadiya | F89: Arpit Makhiyaviya | G89: Vsite-RemoteVal
A90: 84 | B90: 291 | D90: Mohit Solanki | E90: Vivek Ashvinbhai Joshi | F90: Vivek Ashvinbhai Joshi | G90: Intelliante | H90: 49800
A91: 85 | B91: 293 | D91: Moin Qureshi | E91: Dhara Mansukhbhai Basida | F91: RITESH JAIN | G91: Vsite-RemoteVal | H91: 46200
A92: 86 | B92: 292 | D92: Vinod Yogi | E92: Dhara Mansukhbhai Basida | F92: RITESH JAIN | G92: Vsite-RemoteVal | H92: 46200
A93: 87 | B93: 294 | D93: Ankur Paranjpe | E93: Vishal Arvindbhai Panchal | F93: Vishal Arvindbhai Panchal | G93: Genome | H93: 21294
A94: 88 | B94: 297 | D94: Ajay Jikadra | E94: Binal Rajeshbhai Kharecha | F94: Vishal Prajapati | G94: Blitzz | H94: 44400
A95: 89 | B95: 298 | D95: Pallav Koshiya | E95: Bikash Harenhandra Bhakat | F95: Dhananjay Rajeshbhai Dhobi | G95: IFM | H95: 46200
A96: 90 | B96: 300 | D96: Bhavik Kiri | E96: Priyank Mahendrabhai Patel | F96: Priyank Mahendrabhai Patel | G96: MED | H96: 46200
A97: 91 | B97: 301 | D97: Sonukumar Gupta | E97: Vivek Ashvinbhai Joshi | F97: Vishal Arvindbhai Panchal | G97: Genome | H97: 33047
A98: 92 | B98: 302 | D98: Nikunj Joshi | E98: Vishal Arvindbhai Panchal | F98: Vishal Arvindbhai Panchal | G98: Genome | H98: 12089
A99: 105 | B99: 295 | D99: Parbat Singh Chouhan | E99: MehulKumar JayeshKumar Patel | F99: Mayur Vinod kumar Jain | G99: VSI-Nationwide | H99: 49800
A100: 93 | B100: 304 | D100: Ajay Khavas | E100: Anil Babubhai Variya | F100: Vishal Prajapati | G100: Blitzz | H100: 38436
A101: 94 | B101: 305 | D101: Chaitrali Gajjar | E101: Vishal Prajapati | F101: Vishal Prajapati | G101: Blitzz | H101: 38436
... A106: 109 | B106: 303 | D106: Zeelkumar Rabadiya | E106: Rahul Manojkumar Parikh | F106: Rahul Manojkumar Parikh | G106: Sensaii | H106: 26745
A107: 99 | B107: 312 | D107: Viral Suhagiya | E107: Vivek Ashvinbhai Joshi | F107: Arpit Makhiyaviya | G107: Risk Ai
A108: 100 | B108: 311 | D108: Parth Munjani | E108: Samarth Rameshbhai Thesiya | F108: Vishal Arvindbhai Panchal | G108: SculptSoft
A109: 101 | B109: 313 | D109: Pranav Nair | E109: Samarth Rameshbhai Thesiya | F109: Vishal Arvindbhai Panchal | G109: Genome
A110: 108 | B110: 310 | D110: Rajesh Bohra | E110: Ashwin Narendrabhai Patel | F110: Ashwin Narendrabhai Patel | G110: Web Design

Sheet Project-Income VS Salary
A1: Row Labels | B1: Sum of Amount Raised in INR | C1: Sum of Salary to be Paid
A2: KIRTI TRADING COMPANY | B2: 2316992 | C2: 230771
A3: SAGAR SALES | B3: 2121176 | C3: 174969
A4: RELIANCE RETAIL LIMITED | B4: 1554064 | C4: 141583
A5: RAJBHARAT CASHEW COMPANY | B5: 3594388 | C5: 305119
A6: J.K.& CO. | B6: 798270 | C6: 128209
A7: PARTH ENTERPRISE | B7: 1538566 | C7: 75215
A8: SAMIR TRADIND CO. | B8: 1576696 | C8: 141247
A9: RADHA DISTRIBUTORS | B9: 7375162 | C9: 741778
A10: MAHAVIR AGENCIES | B10: 1299618 | C10: 111689
A11: DEVHAR MARKETING PVT.LTD | B11: 3622842 | C11: 355124
A12: RAHI ENTERPRISE | B12: 994086 | C12: 118192
A13: TIRUPATI AGENCIES | B13: 507580 | C13: 127649
... A26: PARSHWANATH TRADERS | B26: 1315526 | C26: 133447
A27: (blank)
A28: Grand Total | B28: 40719888 | C28: 4017627

Sheet Employee_manager_project
A1: Sr No | B1: Employee Code | C1: Column1 | D1: Employee name | E1: Manager Name RM1 | F1: Manager Name RM2 | G1: Table28.Project | H1: Salary to be Paid | I1: Month | J1: Amount Raised in INR | K1: Amount Received in INR | L1: Pending Amount
A2: 1 | B2: 4 | D2: Bansi Jayantibhai Sojitra | E2: MehulKumar JayeshKumar Patel | F2: Mayur Vinod kumar Jain | G2: KIRTI TRADING COMPANY | H2: 49800 | I2: March | J2: 305532 | K2: 582610 | L2: 2895
A3: 49 | B3: 3 | D3: Hetal Arunbhai Agravat | E3: MehulKumar JayeshKumar Patel | F3: Mayur Vinod kumar Jain | G3: SAGAR SALES | H3: 46200 | I3: March | J3: 305532 | K3: 582610 | L3: 2895
A4: 2 | B4: 9 | D4: Dhananjay Rajeshbhai Dhobi | E4: Prashant Thakkar | F4: Prashant Thakkar | G4: RELIANCE RETAIL LIMITED | H4: 9138 | I4: April | J4: 492328 | K4: 429516 | L4: 4762
A5: 3 | B5: 18 | D5: Priyank Mahendrabhai Patel | E5: Prashant Thakkar | F5: Prashant Thakkar | G5: RAJBHARAT CASHEW COMPANY | H5: -10374 | I5: April | J5: 740296 | K5: 228370 | L5: 7215
A6: 4 | B6: 13 | D6: Vivek Ashvinbhai Joshi | E6: Prashant Thakkar | F6: Prashant Thakkar | G6: KIRTI TRADING COMPANY | H6: 30556
A7: 5 | B7: 22 | D7: Binal Rajeshbhai Kharecha | E7: Anil Babubhai Variya | F7: Vishal Prajapati | G7: SAGAR SALES | H7: 49800 | I7: April | J7: 740296 | K7: 228370 | L7: 7215
A8: 6 | B8: 25 | D8: Kush Kiritkumar Jadia | E8: RITESH JAIN | F8: RITESH JAIN | G8: RELIANCE RETAIL LIMITED | H8: 40045 | I8: March | J8: 530868 | K8: 621560 | L8: 2420
A9: 7 | B9: 28 | D9: Vishal Arvindbhai Panchal | E9: Prashant Thakkar | F9: Prashant Thakkar | G9: J.K.& CO. | H9: 32209 | I9: March | J9: 253790 | K9: 178678 | L9: 7821
A10: 8 | B10: 38 | D10: Pankti Milap Patel | E10: Arpit Makhiyaviya | F10: Arpit Makhiyaviya | G10: PARTH ENTERPRISE | H10: 24133 | I10: March | J10: 253790 | K10: 178678 | L10: 7821
A11: 9 | B11: 42 | D11: Ashwin Narendrabhai Patel | E11: Vishal Prajapati | F11: Vishal Prajapati | G11: SAMIR TRADIND CO. | H11: 49800 | I11: April | J11: 740296 | K11: 228370 | L11: 7215
A12: 10 | B12: 43 | D12: Mudit Meghraj Parakh | E12: Arpit Makhiyaviya | F12: Arpit Makhiyaviya | G12: RAJBHARAT CASHEW COMPANY | H12: 40032 | I12: March | J12: 253790 | K12: 178678 | L12: 7821
A13: 11 | B13: 45 | D13: Nitin Tribhovan Makwana | E13: Vishal Prajapati | F13: Vishal Prajapati | G13: KIRTI TRADING COMPANY | H13: 58015 | I13: April | J13: 740296 | K13: 228370 | L13: 7215
A14: 12 | B14: 50 | D14: Kinjal Bipinbhai Hingu | E14: Nitin Tribhovan Makwana | F14: Vishal Prajapati | G14: RADHA DISTRIBUTORS | H14: 46200 | I14: April | J14: 740296 | K14: 228370 | L14: 7215
A15: 13 | B15: 51 | D15: Kalpesh NaginBhai Patel | E15: Vishal Prajapati | F15: Vishal Prajapati | G15: RADHA DISTRIBUTORS | H15: 42051 | I15: April | J15: 740296 | K15: 228370 | L15: 7215
A16: 14 | B16: 66 | D16: Avani Ashvinbhai Patel | E16: Arpit Makhiyaviya | F16: Arpit Makhiyaviya | G16: RADHA DISTRIBUTORS | H16: 11978 | I16: March | J16: 253790 | K16: 178678 | L16: 7821
A17: 15 | B17: 69 | D17: Samarth Rameshbhai Thesiya | E17: Vishal Arvindbhai Panchal | F17: Vishal Arvindbhai Panchal | G17: RADHA DISTRIBUTORS | H17: 49800 | I17: March | J17: 253790 | K17: 178678 | L17: 7821
A18: 16 | B18: 76 | D18: Jaldhi Mahendrabhai Darji | E18: MehulKumar JayeshKumar Patel | F18: Mayur Vinod kumar Jain | G18: MAHAVIR AGENCIES | H18: 49800 | I18: March | J18: 305532 | K18: 582610 | L18: 2895
A19: 17 | B19: 77 | D19: Kinjan Leela Jain | E19: Nilesh Dhirajlal Thakkar | F19: RITESH JAIN | G19: DEVHAR MARKETING PVT.LTD | H19: 39174 | I19: March | J19: 530868 | K19: 621560 | L19: 2420
A20: 18 | B20: 85 | D20: Mansi Shaileshbhai Kakkad | E20: Prashant Thakkar | F20: Prashant Thakkar | G20: DEVHAR MARKETING PVT.LTD | H20: 34103
A21: 19 | B21: 90 | D21: Darshan Rasikbhai Chudasama | E21: Pankti Milap Patel | F21: Arpit Makhiyaviya | G21: DEVHAR MARKETING PVT.LTD | H21: 32875 | I21: March | J21: 253790 | K21: 178678 | L21: 7821
A22: 20 | B22: 91 | D22: Ronak Prakashbhai Makhiyaviya | E22: Anil Babubhai Variya | F22: Vishal Prajapati | G22: RAHI ENTERPRISE | H22: 46200 | I22: April | J22: 740296 | K22: 228370 | L22: 7215
A23: 21 | B23: 95 | D23: Nishant Nitin Gajjar | E23: Arpit Makhiyaviya | F23: Arpit Makhiyaviya | G23: TIRUPATI AGENCIES | H23: 49800 | I23: March | J23: 253790 | K23: 178678 | L23: 7821
A24: 22 | B24: 100 | D24: Shital Ravi Gohil | E24: Mayur Vinod kumar Jain | F24: Mayur Vinod kumar Jain | G24: RAVI SALES | H24: 46200 | I24: March | J24: 305532 | K24: 582610 | L24: 2895
A25: 23 | B25: 101 | D25: Kaushal BharatBhai Jayswal | E25: MehulKumar JayeshKumar Patel | F25: Mayur Vinod kumar Jain | G25: RAVI SALES | H25: 54377 | I25: March | J25: 305532 | K25: 582610 | L25: 2895
A26: 24 | B26: 104 | D26: MehulKumar JayeshKumar Patel | E26: Mayur Vinod kumar Jain | F26: Mayur Vinod kumar Jain | G26: JALARAM SALES AGENCY | H26: 46226 | I26: March | J26: 305532 | K26: 582610 | L26: 2895
A27: 25 | B27: 112 | D27: Sahilkumar Amrutlal Bhuva | E27: Vishakha Bharatbhai Kathrecha | F27: RITESH JAIN | G27: KANERIYA OIL INDUSTRIES | H27: 49800 | I27: March | J27: 530868 | K27: 621560 | L27: 2420
A28: 26 | B28: 114 | D28: Paresh Rameshbhai Devatval | E28: Dhananjay Rajeshbhai Dhobi | F28: Dhananjay Rajeshbhai Dhobi | G28: NTC | H28: 33838 | I28: April | J28: 492328 | K28: 429516 | L28: 4762
A29: 27 | B29: 115 | D29: Pragneshkumar Lakhmanbhai Meniya | E29: Nilesh Dhirajlal Thakkar | F29: RITESH JAIN | G29: KQ BRO-SIS FOODS ENTERPRISE | H29: 49800 | I29: March | J29: 530868 | K29: 621560 | L29: 2420
A30: 28 | B30: 118 | D30: Mayur Vinod kumar Jain | E30: Prashant Thakkar | F30: Prashant Thakkar | G30: NTC | H30: 3590 | I30: March | J30: 305532 | K30: 582610 | L30: 2895
A31: 29 | B31: 121 | D31: Nensi Harsh Dhingani | E31: Vishal Arvindbhai Panchal | F31: Vishal Arvindbhai Panchal | G31: NTC | H31: -50503 | I31: March | J31: 253790 | K31: 178678 | L31: 7821
A32: 30 | B32: 128 | D32: Dhara Mansukhbhai Basida | E32: RITESH JAIN | F32: RITESH JAIN | G32: JAY AMBE TRADERS | H32: 5655 | I32: March | J32: 530868 | K32: 621560 | L32: 2420
... A35: 33 | B35: 131 | D35: Bikash Harenhandra Bhakat | E35: Dhananjay Rajeshbhai Dhobi | F35: Dhananjay Rajeshbhai Dhobi | G35: RADHA DISTRIBUTORS | H35: 44950 | I35: April | J35: 492328 | K35: 429516 | L35: 4762
A36: 34 | B36: 132 | D36: Dolly Dinesh Kumar Shah | E36: Chetana Ramasare Ravat | F36: Chetana Ramasare Ravat | G36: SHAURYA ENTERPRISE | H36: 49800
A37: 35 | B37: 133 | D37: Jigar Deepak Bhinde | E37: Ashwin Narendrabhai Patel | F37: Ashwin Narendrabhai Patel | G37: SHAURYA ENTERPRISE | H37: 40200
A38: 36 | B38: 137 | D38: Chetana Ramasare Ravat | E38: Prashant Thakkar | F38: Prashant Thakkar | G38: R C SALES | H38: 12867
A39: 37 | B39: 140 | D39: Arpita Harshadbhai Patel | E39: MehulKumar JayeshKumar Patel | F39: Mayur Vinod kumar Jain | G39: SAMIR TRADIND CO. | H39: 49800 | I39: March | J39: 305532 | K39: 582610 | L39: 2895
A40: 38 | B40: 141 | D40: Ashish Mansukhbhai Chaniyara | E40: Ashwin Narendrabhai Patel | F40: Vishal Prajapati | G40: RAJBHARAT CASHEW COMPANY | H40: 49800 | I40: April | J40: 740296 | K40: 228370 | L40: 7215
A41: 39 | B41: 146 | D41: Modi Vandana Hiteshbhai | E41: Kalpesh NaginBhai Patel | F41: Vishal Prajapati | G41: KIRTI TRADING COMPANY | H41: 46200 | I41: April | J41: 740296 | K41: 228370 | L41: 7215
A42: 40 | B42: 147 | D42: Manish Ambadas Patil | E42: Pankti Milap Patel | F42: Arpit Makhiyaviya | G42: SHAH TOKARSHI TRIBHOVANDAS | H42: 44190 | I42: March | J42: 253790 | K42: 178678 | L42: 7821
A43: 41 | B43: 151 | D43: Anmol Hariombhai Chaudhary | E43: Rahul Manojkumar Parikh | F43: Rahul Manojkumar Parikh | G43: SAGAR SALES | H43: 42174 | I43: January | J43: 544480 | K43: 308484 | L43: 6238
A44: 42 | B44: 152 | D44: Himshree Himanshu Dave | E44: Chetana Ramasare Ravat | F44: Chetana Ramasare Ravat | G44: RELIANCE RETAIL LIMITED | H44: 46200
A45: 43 | B45: 157 | D45: Sumit Kumar Nainiwal | E45: Rahul Manojkumar Parikh | F45: Rahul Manojkumar Parikh | G45: J.K.& CO. | H45: 49800 | I45: January | J45: 544480 | K45: 308484 | L45: 6238
A46: 44 | B46: 161 | D46: Rahul Manojkumar Parikh | E46: RITESH JAIN | F46: RITESH JAIN | G46: PARTH ENTERPRISE | H46: 4882 | I46: January | J46: 544480 | K46: 308484 | L46: 6238
A47: 45 | B47: 164 | D47: Anil Babubhai Variya | E47: Vishal Prajapati | F47: Vishal Prajapati | G47: SOMNATH RICE MILL | H47: 51922 | I47: April | J47: 740296 | K47: 228370 | L47: 7215
A48: 46 | B48: 165 | D48: Bhatt Krupa Pradipbhai | E48: ashish Sharma | F48: RITESH JAIN | G48: SHIVAM AGRO PROCESSOR | H48: 49800 | I48: March | J48: 530868 | K48: 621560 | L48: 2420
A49: 47 | B49: 166 | D49: RITESH JAIN | E49: Prashant Thakkar | F49: Prashant Thakkar | G49: HARESHKUMAR HASSANAND | H49: 2882 | I49: March | J49: 530868 | K49: 621560 | L49: 2420
A50: 48 | B50: 168 | D50: Nilesh Dhirajlal Thakkar | E50: RITESH JAIN | F50: RITESH JAIN | G50: RAJBHARAT CASHEW COMPANY | H50: 43820 | I50: March | J50: 530868 | K50: 621560 | L50: 2420
A51: 50 | B51: 182 | D51: Nirali Hirenkumar Joshi | E51: Vivek Ashvinbhai Joshi | F51: Arpit Makhiyaviya | G51: PARSHWANATH TRADERS | H51: 46200
A52: 102 | B52: 179 | D52: Kunal M Bhavsar | E52: Vivek Ashvinbhai Joshi | F52: Arpit Makhiyaviya | G52: RAJBHARAT CASHEW COMPANY | H52: 36041 | I52: March | J52: 253790 | K52: 178678 | L52: 7821
A53: 51 | B53: 187 | D53: Vishakha Bharatbhai Kathrecha | E53: RITESH JAIN | F53: Arpit Makhiyaviya | G53: PARSHWANATH TRADERS | H53: 19753 | I53: March | J53: 530868 | K53: 621560 | L53: 2420
A54: 52 | B54: 116 | D54: Arjun Lal Rabari | E54: Prashant Thakkar | F54: Prashant Thakkar | G54: RADHA DISTRIBUTORS | H54: 29200
A55: 53 | B55: 225 | D55: Bharat Kadchha | E55: Dhara Mansukhbhai Basida | F55: RITESH JAIN | G55: RADHA DISTRIBUTORS | H55: 46200 | I55: March | J55: 530868 | K55: 621560 | L55: 2420
A56: 54 | B56: 222 | D56: Mehul Girishbhai Rathod | E56: Dhara Mansukhbhai Basida | F56: Mayur Vinod kumar Jain | G56: RADHA DISTRIBUTORS | H56: 49800 | I56: March | J56: 530868 | K56: 621560 | L56: 2420
A57: 55 | B57: 227 | D57: Rilav Thakkar | E57: Arpit Makhiyaviya | F57: Arpit Makhiyaviya | G57: RADHA DISTRIBUTORS | H57: 46200
A58: 76 | B58: 226 | D58: Vaishnavi Patel | E58: Vishal Prajapati | F58: Vishal Prajapati | G58: MAHAVIR AGENCIES | H58: 49800 | I58: April | J58: 740296 | K58: 228370 | L58: 7215
A59: 56 | B59: 236 | D59: Ankit Prajapati | E59: Vishal Arvindbhai Panchal | F59: Vishal Arvindbhai Panchal | G59: DEVHAR MARKETING PVT.LTD | H59: 31900 | I59: March | J59: 253790 | K59: 178678 | L59: 7821
A60: 57 | B60: 237 | D60: Walmik Magar | E60: Rahul Manojkumar Parikh | F60: Rahul Manojkumar Parikh | G60: DEVHAR MARKETING PVT.LTD | H60: 46200 | I60: January | J60: 544480 | K60: 308484 | L60: 6238
A61: 106 | B61: 235 | D61: Premal Parekh | E61: Vivek Ashvinbhai Joshi | F61: Vishal Arvindbhai Panchal | G61: DEVHAR MARKETING PVT.LTD | H61: 44200 | I61: March | J61: 253790 | K61: 178678 | L61: 7821
A62: 58 | B62: 243 | D62: Fatema Dungarawala | E62: Darshan Rasikbhai Chudasama | F62: Arpit Makhiyaviya | G62: RAHI ENTERPRISE | H62: 45047 | I62: March | J62: 253790 | K62: 178678 | L62: 7821
A63: 59 | B63: 241 | D63: Harsha Sharma | E63: Darshan Rasikbhai Chudasama | F63: Arpit Makhiyaviya | G63: TIRUPATI AGENCIES | H63: 53085 | I63: March | J63: 253790 | K63: 178678 | L63: 7821
A64: 60 | B64: 244 | D64: Yash Bhatt | E64: Mayur Vinod kumar Jain | F64: Mayur Vinod kumar Jain | G64: RAVI SALES | H64: 46200 | I64: May | J64: 466416 | K64: 425990 | L64: 4805
A65: 61 | B65: 247 | D65: Harsh Goyal | E65: RITESH JAIN | F65: RITESH JAIN | G65: RAVI SALES | H65: 46200 | I65: March | J65: 530868 | K65: 621560 | L65: 2420
A66: 62 | B66: 249 | D66: Akash Rathor | E66: Samarth Rameshbhai Thesiya | F66: Vishal Arvindbhai Panchal | G66: JALARAM SALES AGENCY | H66: 49800 | I66: March | J66: 253790 | K66: 178678 | L66: 7821
A67: 63 | B67: 253 | D67: Suresh Kumar Sen | E67: Vishakha Bharatbhai Kathrecha/Vishal Panchal | F67: Arpit Makhiyaviya | G67: KANERIYA OIL INDUSTRIES | H67: 44346
A68: 104 | B68: 245 | D68: Krunal Lunagariya | E68: Dhananjay Rajeshbhai Dhobi | F68: Dhananjay Rajeshbhai Dhobi | G68: NTC | H68: 33137 | I68: April | J68: 492328 | K68: 429516 | L68: 4762
A69: 64 | B69: 255 | D69: Bhumi Shah | E69: Darshan Rasikbhai Chudasama | F69: Arpit Makhiyaviya | G69: KQ BRO-SIS FOODS ENTERPRISE | H69: 46200 | I69: March | J69: 253790 | K69: 178678 | L69: 7821
A70: 103 | B70: 246 | D70: Priya Desai | E70: Chetana Ramasare Ravat | F70: Chetana Ramasare Ravat | G70: NTC | H70: 49800
A71: 65 | B71: 262 | D71: Dheeraj Chadhar | E71: ashish Sharma | F71: RITESH JAIN | G71: NTC | H71: 46200 | I71: March | J71: 530868 | K71: 621560 | L71: 2420
A72: 66 | B72: 264 | D72: Akshay Patel | E72: ashish Sharma | F72: RITESH JAIN | G72: JAY AMBE TRADERS | H72: 42944 | I72: March | J72: 530868 | K72: 621560 | L72: 2420
A73: 67 | B73: 265 | D73: Vishal Prajapati | E73: Priyank Mahendrabhai Patel | F73: Priyank Mahendrabhai Patel | G73: RADHA DISTRIBUTORS | H73: 46765 | I73: April | J73: 740296 | K73: 228370 | L73: 7215
A74: 68 | B74: 267 | D74: Kapil Thakar | E74: ashish Sharma | F74: RITESH JAIN | G74: RADHA DISTRIBUTORS | H74: 49800 | I74: March | J74: 530868 | K74: 621560 | L74: 2420
A75: 69 | B75: 270 | D75: Hardik Vaghela | E75: Arpit Makhiyaviya | F75: Arpit Makhiyaviya | G75: RADHA DISTRIBUTORS | H75: 46200
A76: 77 | B76: 257 | D76: Ashish Sharma | E76: RITESH JAIN | F76: RITESH JAIN | G76: SHAURYA ENTERPRISE | H76: 37201 | I76: March | J76: 530868 | K76: 621560 | L76: 2420
A77: 70 | B77: 271 | D77: Vainik Kakadiya | E77: Vishakha Bharatbhai Kathrecha | F77: Arpit Makhiyaviya | G77: SHAURYA ENTERPRISE | H77: 46200 | I77: March | J77: 253790 | K77: 178678 | L77: 7821
A78: 71 | B78: 272 | D78: Sanjay Prajapat | E78: Nilesh Dhirajlal Thakkar | F78: RITESH JAIN | G78: R C SALES | H78: 49800 | I78: March | J78: 530868 | K78: 621560 | L78: 2420
A79: 72 | B79: 273 | D79: Akash Sheth | E79: Kush Kiritkumar Jadia | F79: RITESH JAIN | G79: SAMIR TRADIND CO. | H79: 41647 | I79: March | J79: 530868 | K79: 621560 | L79: 2420
A80: 73 | B80: 276 | D80: Anandi Pattani | E80: Rahul Manojkumar Parikh | F80: Rahul Manojkumar Parikh | G80: RAJBHARAT CASHEW COMPANY | H80: 49800 | I80: January | J80: 544480 | K80: 308484 | L80: 6238
A81: 74 | B81: 277 | D81: Rajatkumar Patel | E81: Nilesh Dhirajlal Thakkar | F81: RITESH JAIN | G81: KIRTI TRADING COMPANY | H81: 46200 | I81: March | J81: 530868 | K81: 621560 | L81: 2420
A82: 78 | B82: 269 | D82: Bansi Gothi | E82: Vishakha Bharatbhai Kathrecha | F82: Arpit Makhiyaviya | G82: SHAH TOKARSHI TRIBHOVANDAS | H82: 49800 | I82: March | J82: 253790 | K82: 178678 | L82: 7821
A83: 75 | B83: 279 | D83: Shubham Gupta | E83: Kush Kiritkumar Jadia | F83: RITESH JAIN | G83: SAGAR SALES | H83: 36795 | I83: March | J83: 530868 | K83: 621560 | L83: 2420
A84: 79 | B84: 274 | D84: Chirag Gujarati | E84: Kush Kiritkumar Jadia | F84: RITESH JAIN | G84: RELIANCE RETAIL LIMITED | H84: 46200 | I84: March | J84: 530868 | K84: 621560 | L84: 2420
A85: 80 | B85: 280 | D85: Digvijaysinh Zankat | E85: Arpit Makhiyaviya | F85: Arpit Makhiyaviya | G85: J.K.& CO. | H85: 46200
A86: 81 | B86: 284 | D86: Vivek Busa | E86: Anil Babubhai Variya | F86: Vishal Prajapati | G86: PARTH ENTERPRISE | H86: 46200 | I86: April | J86: 740296 | K86: 228370 | L86: 7215
A87: 82 | B87: 285 | D87: Kruttika Patel | E87: Mansi Shaileshbhai Kakkad | F87: Mansi Shaileshbhai Kakkad | G87: SOMNATH RICE MILL | H87: 49800
A88: 107 | B88: 278 | D88: Henil Shah | E88: Ankit Prajapati | F88: Vivek Ashvinbhai Joshi | G88: SHIVAM AGRO PROCESSOR | H88: 46200
A89: 83 | B89: 290 | D89: Vedkumar Patel | E89: Vainik Kakadiya | F89: Arpit Makhiyaviya | G89: HARESHKUMAR HASSANAND | I89: March | J89: 530868 | K89: 621560 | L89: 2420
A90: 84 | B90: 291 | D90: Mohit Solanki | E90: Vivek Ashvinbhai Joshi | F90: Vivek Ashvinbhai Joshi | G90: RAJBHARAT CASHEW COMPANY | H90: 49800
A91: 85 | B91: 293 | D91: Moin Qureshi | E91: Dhara Mansukhbhai Basida | F91: RITESH JAIN | G91: PARSHWANATH TRADERS | H91: 46200 | I91: March | J91: 530868 | K91: 621560 | L91: 2420
A92: 86 | B92: 292 | D92: Vinod Yogi | E92: Dhara Mansukhbhai Basida | F92: RITESH JAIN | G92: RAJBHARAT CASHEW COMPANY | H92: 46200 | I92: March | J92: 530868 | K92: 621560 | L92: 2420
A93: 87 | B93: 294 | D93: Ankur Paranjpe | E93: Vishal Arvindbhai Panchal | F93: Vishal Arvindbhai Panchal | G93: PARSHWANATH TRADERS | H93: 21294 | I93: March | J93: 253790 | K93: 178678 | L93: 7821
A94: 88 | B94: 297 | D94: Ajay Jikadra | E94: Binal Rajeshbhai Kharecha | F94: Vishal Prajapati | G94: RADHA DISTRIBUTORS | H94: 44400 | I94: April | J94: 740296 | K94: 228370 | L94: 7215
A95: 89 | B95: 298 | D95: Pallav Koshiya | E95: Bikash Harenhandra Bhakat | F95: Dhananjay Rajeshbhai Dhobi | G95: RADHA DISTRIBUTORS | H95: 46200 | I95: April | J95: 492328 | K95: 429516 | L95: 4762
A96: 90 | B96: 300 | D96: Bhavik Kiri | E96: Priyank Mahendrabhai Patel | F96: Priyank Mahendrabhai Patel | G96: RADHA DISTRIBUTORS | H96: 46200
A97: 91 | B97: 301 | D97: Sonukumar Gupta | E97: Vivek Ashvinbhai Joshi | F97: Vishal Arvindbhai Panchal | G97: RADHA DISTRIBUTORS | H97: 33047 | I97: March | J97: 253790 | K97: 178678 | L97: 7821
A98: 92 | B98: 302 | D98: Nikunj Joshi | E98: Vishal Arvindbhai Panchal | F98: Vishal Arvindbhai Panchal | G98: MAHAVIR AGENCIES | H98: 12089 | I98: March | J98: 253790 | K98: 178678 | L98: 7821
A99: 105 | B99: 295 | D99: Parbat Singh Chouhan | E99: MehulKumar JayeshKumar Patel | F99: Mayur Vinod kumar Jain | G99: DEVHAR MARKETING PVT.LTD | H99: 49800 | I99: March | J99: 305532 | K99: 582610 | L99: 2895
A100: 93 | B100: 304 | D100: Ajay Khavas | E100: Anil Babubhai Variya | F100: Vishal Prajapati | G100: DEVHAR MARKETING PVT.LTD | H100: 38436 | I100: April | J100: 740296 | K100: 228370 | L100: 7215
A101: 94 | B101: 305 | D101: Chaitrali Gajjar | E101: Vishal Prajapati | F101: Vishal Prajapati | G101: DEVHAR MARKETING PVT.LTD | H101: 38436 | I101: April | J101: 740296 | K101: 228370 | L101: 7215
A102: 95 | B102: 306 | D102: Fenil Kanjiya | E102: Ronak Prakashbhai Makhiyaviya | F102: Vishal Prajapati | G102: RAHI ENTERPRISE | H102: 26945
...

Sheet Sheet5
A1: Sr No | B1: Employee Code | C1: Column1 | D1: Employee name | E1: Manager Name RM1 | F1: Manager Name RM2
A2: 1 | B2: 4 | D2: Bansi Jayantibhai Sojitra | E2: MehulKumar JayeshKumar Patel | F2: Mayur Vinod kumar Jain
A3: 2 | B3: 9 | D3: Dhananjay Rajeshbhai Dhobi | E3: Prashant Thakkar | F3: Prashant Thakkar
A4: 3 | B4: 18 | D4: Priyank Mahendrabhai Patel | E4: Prashant Thakkar | F4: Prashant Thakkar
A5: 4 | B5: 13 | D5: Vivek Ashvinbhai Joshi | E5: Prashant Thakkar | F5: Prashant Thakkar
A6: 5 | B6: 22 | D6: Binal Rajeshbhai Kharecha | E6: Anil Babubhai Variya | F6: Vishal Prajapati
A7: 6 | B7: 25 | D7: Kush Kiritkumar Jadia | E7: RITESH JAIN | F7: RITESH JAIN
A8: 7 | B8: 28 | D8: Vishal Arvindbhai Panchal | E8: Prashant Thakkar | F8: Prashant Thakkar
A9: 8 | B9: 38 | D9: Pankti Milap Patel | E9: Arpit Makhiyaviya | F9: Arpit Makhiyaviya
A10: 9 | B10: 42 | D10: Ashwin Narendrabhai Patel | E10: Vishal Prajapati | F10: Vishal Prajapati
A11: 10 | B11: 43 | D11: Mudit Meghraj Parakh | E11: Arpit Makhiyaviya | F11: Arpit Makhiyaviya
A12: 11 | B12: 45 | D12: Nitin Tribhovan Makwana | E12: Vishal Prajapati | F12: Vishal Prajapati
A13: 12 | B13: 50 | D13: Kinjal Bipinbhai Hingu | E13: Nitin Tribhovan Makwana | F13: Vishal Prajapati
... A110: 109 | B110: 303 | D110: Zeelkumar Rabadiya | E110: Rahul Manojkumar Parikh | F110: Rahul Manojkumar Parikh

Sheet Sheet6
A1: Sr No | B1: Code | C1: Employee Name | D1: Project
A2: 1 | B2: 3 | C2: Hetal Arunbhai Agravat | D2: VSI-Nationwide
A3: 2 | B3: 4 | C3: Bansi Jayantibhai Sojitra | D3: VSI-Nationwide
A4: 3 | B4: 9 | C4: Dhananjay Rajeshbhai Dhobi | D4: IFM
A5: 4 | B5: 13 | C5: Vivek Ashvinbhai Joshi | D5: Risk AI/Genome
A6: 5 | B6: 18 | C6: Priyank Mahendrabhai Patel | D6: Blitzz
A7: 6 | B7: 22 | C7: Binal Rajeshbhai Kharecha | D7: Blitzz
A8: 7 | B8: 25 | C8: Kush Kiritkumar Jadia | D8: Vsite-RemoteVal
A9: 8 | B9: 28 | C9: Vishal Arvindbhai Panchal | D9: Genome
A10: 9 | B10: 38 | C10: Pankti Milap Patel | D10: Genome
A11: 10 | B11: 42 | C11: Ashwin Narendrabhai Patel | D11: Blitzz
A12: 11 | B12: 43 | C12: Mudit Meghraj Parakh | D12: Genome
A13: 12 | B13: 45 | C13: Nitin Tribhovan Makwana | D13: Blitzz
... A110: 109 | B110: 116 | C110: Arjun Lal Rabari | D110: Admin

Sheet Project_income
A1: Sr. No. | B1: Buyer | C1: Invoice Date | D1: Invoice Month | E1: Column2 | F1: Invoice# | G1: Due Date | H1: Invoice Amount | I1: Received Amount in INR | J1: Received Amount | K1: Received Date | L1: Pending Amount | M1: Column1 | O1: Buyer | P1: Month | Q1: Amount Raised | R1: Amount Raised in INR | S1: Received Amount | T1: Amount Received in INR | U1: Pending Amount | V1: Table28.Project
A2: 1 | B2: RADHA DISTRIBUTORS | C2: 44652 | D2: 44986 | E2: =TEXT(Project_Payments1617[[#This Row],[Invoice Month]],"mmmm") -> March | F2: 1 | G2: 45023 | H2: 10000 | I2: =J2*82 -> 621560 | J2: 7580 | K2: 44657 | L2: =H2-J2 -> 2420 | M2: =3516668.21/47096 -> 74.67021 | O2: RADHA DISTRIBUTORS | P2: March | Q2: 6474 | R2: =Table35[[#This Row],[Amount Raised]]*82 -> 530868 | S2: 7580 | T2: =Table35[[#This Row],[Received Amount]]*82 -> 621560 | U2: 2420 | V2: RADHA DISTRIBUTORS
A3: 2 | B3: RADHA DISTRIBUTORS | C3: 44654 | D3: 44621 | E3: =TEXT(Project_Payments1617[[#This Row],[Invoice Month]],"mmmm") -> March | F3: 2 | G3: 44668 | H3: 10000 | I3: =J3*82 -> 178678 | J3: 2179 | K3: 44670 | L3: =H3-J3 -> 7821 | O3: RADHA DISTRIBUTORS | P3: March | Q3: 3095 | R3: =Table35[[#This Row],[Amount Raised]]*82 -> 253790 | S3: 2179 | T3: =Table35[[#This Row],[Received Amount]]*82 -> 178678 | U3: 7821 | V3: RADHA DISTRIBUTORS
A4: 3 | B4: RADHA DISTRIBUTORS | C4: 44655 | D4: 44621 | E4: =TEXT(Project_Payments1617[[#This Row],[Invoice Month]],"mmmm") -> March | F4: 3 | G4: 44664 | H4: 10000 | I4: =J4*82 -> 154816 | J4: 1888 | K4: 44669 | L4: =H4-J4 -> 8112 | O4: RADHA DISTRIBUTORS | P4: March | Q4: 5716 | R4: =Table35[[#This Row],[Amount Raised]]*82 -> 468712 | S4: 1888 | T4: =Table35[[#This Row],[Received Amount]]*82 -> 154816 | U4: 8112 | V4: RADHA DISTRIBUTORS
A5: 4 | B5: RADHA DISTRIBUTORS | C5: 44656 | D5: 44621 | E5: =TEXT(Project_Payments1617[[#This Row],[Invoice Month]],"mmmm") -> March | F5: 4 | G5: 44662 | H5: 10000 | I5: =J5*82 -> 582610 | J5: 7105 | K5: 44669 | L5: =H5-J5 -> 2895 | O5: RADHA DISTRIBUTORS | P5: March | Q5: 3726 | R5: =Table35[[#This Row],[Amount Raised]]*82 -> 305532 | S5: 7105 | T5: =Table35[[#This Row],[Received Amount]]*82 -> 582610 | U5: 2895 | V5: RADHA DISTRIBUTORS
A6: 5 | B6: MAHAVIR AGENCIES | C6: 44665 | D6: Feb-Mar | E6: =TEXT(Project_Payments1617[[#This Row],[Invoice Month]],"mmmm") -> Feb-Mar | F6: 5 | G6: 44674 | H6: 10000 | I6: =J6*82 -> 180072 | J6: 2196 | K6: 44680 | L6: =H6-J6 -> 7804 | O6: RADHA DISTRIBUTORS | P6: Feb-Mar | Q6: 6293 | R6: =Table35[[#This Row],[Amount Raised]]*82 -> 516026 | S6: 2196 | T6: =Table35[[#This Row],[Received Amount]]*82 -> 180072 | U6: 7804 | V6: MAHAVIR AGENCIES
A7: 6 | B7: DEVHAR MARKETING PVT.LTD | C7: 44672 | D7: 44652 | E7: =TEXT(Project_Payments1617[[#This Row],[Invoice Month]],"mmmm") -> April | F7: 6 | G7: 44686 | H7: 10000 | I7: =J7*82 -> 429516 | J7: 5238 | K7: 44701 | L7: =H7-J7 -> 4762 | M7: TDS | O7: RADHA DISTRIBUTORS | P7: April | Q7: 6004 | R7: =Table35[[#This Row],[Amount Raised]]*82 -> 492328 | S7: 5238 | T7: =Table35[[#This Row],[Received Amount]]*82 -> 429516 | U7: 4762 | V7: DEVHAR MARKETING PVT.LTD
A8: 7 | B8: DEVHAR MARKETING PVT.LTD | C8: 44676 | D8: 44652 | E8: =TEXT(Project_Payments1617[[#This Row],[Invoice Month]],"mmmm") -> April | F8: 7 | G8: 44690 | H8: 10000 | I8: =J8*82 -> 480848 | J8: 5864 | K8: 44701 | L8: =H8-J8 -> 4136 | M8: TDS | O8: MAHAVIR AGENCIES | P8: April | Q8: 7906 | R8: =Table35[[#This Row],[Amount Raised]]*82 -> 648292 | S8: 5864 | T8: =Table35[[#This Row],[Received Amount]]*82 -> 480848 | U8: 4136 | V8: DEVHAR MARKETING PVT.LTD
A9: 8 | B9: DEVHAR MARKETING PVT.LTD | C9: 44679 | E9: =TEXT(Project_Payments1617[[#This Row],[Invoice Month]],"mmmm") -> January | F9: 8 | G9: 44688 | H9: 10000 | I9: =J9*82 -> 308484 | J9: 3762 | K9: 44743 | L9: =H9-J9 -> 6238 | O9: DEVHAR MARKETING PVT.LTD | P9: January | Q9: 6640 | R9: =Table35[[#This Row],[Amount Raised]]*82 -> 544480 | S9: 3762 | T9: =Table35[[#This Row],[Received Amount]]*82 -> 308484 | U9: 6238 | V9: DEVHAR MARKETING PVT.LTD
A10: 9 | B10: RAHI ENTERPRISE | C10: 44682 | D10: 44652 | E10: =TEXT(Project_Payments1617[[#This Row],[Invoice Month]],"mmmm") -> April | F10: 9 | G10: 44688 | H10: 10000 | I10: =J10*82 -> 531934 | J10: 6487 | K10: 44686 | L10: =H10-J10 -> 3513 | O10: DEVHAR MARKETING PVT.LTD | P10: April | Q10: 7456 | R10: =Table35[[#This Row],[Amount Raised]]*82 -> 611392 | S10: 6487 | T10: =Table35[[#This Row],[Received Amount]]*82 -> 531934 | U10: 3513 | V10: RAHI ENTERPRISE
A11: 10 | B11: TIRUPATI AGENCIES | C11: 44683 | D11: 44652 | E11: =TEXT(Project_Payments1617[[#This Row],[Invoice Month]],"mmmm") -> April | F11: 10 | G11: 44697 | H11: 10000 | I11: =J11*82 -> 228370 | J11: 2785 | K11: 44691 | L11: =H11-J11 -> 7215 | M11: =1798358.9/23474 -> 76.610671 | O11: DEVHAR MARKETING PVT.LTD | P11: April | Q11: 9028 | R11: =Table35[[#This Row],[Amount Raised]]*82 -> 740296 | S11: 2785 | T11: =Table35[[#This Row],[Received Amount]]*82 -> 228370 | U11: 7215 | V11: TIRUPATI AGENCIES
A12: 11 | B12: RAVI SALES | C12: 44683 | D12: 44652 | E12: =TEXT(Project_Payments1617[[#This Row],[Invoice Month]],"mmmm") -> April | F12: 11 | G12: 44692 | H12: 10000 | I12: =J12*82 -> 341776 | J12: 4168 | K12: 44698 | L12: =H12-J12 -> 5832 | O12: DEVHAR MARKETING PVT.LTD | P12: April | Q12: 4587 | R12: =Table35[[#This Row],[Amount Raised]]*82 -> 376134 | S12: 4168 | T12: =Table35[[#This Row],[Received Amount]]*82 -> 341776 | U12: 5832 | V12: RAVI SALES
A13: 12 | B13: RAVI SALES | C13: 44685 | D13: 44652 | E13: =TEXT(Project_Payments1617[[#This Row],[Invoice Month]],"mmmm") -> April | F13: 12 | G13: 44699 | H13: 10000 | I13: =J13*82 -> 326114 | J13: 3977 | K13: 44699 | L13: =H13-J13 -> 6023 | O13: RAHI ENTERPRISE | P13: April | Q13: 2181 | R13: =Table35[[#This Row],[Amount Raised]]*82 -> 178842 | S13: 3977 | T13: =Table35[[#This Row],[Received Amount]]*82 -> 326114 | U13: 6023 | V13: RAVI SALES
A14: 13 | B14: JALARAM SALES AGENCY | C14: Invoice# 13 Skipping for any adjustment | O14: Invoice# 13 Skipping for any adjustment | Q14: 4363 | R14: =Table35[[#This Row],[Amount Raised]]*82 -> 357766 | T14: =Table35[[#This Row],[Received Amount]]*82 -> 0 | V14: JALARAM SALES AGENCY
A15: 14 | B15: KANERIYA OIL INDUSTRIES | C15: 44685 | D15: 44652 | E15: =TEXT(Project_Payments1617[[#This Row],[Invoice Month]],"mmmm") -> April | F15: 14 | G15: 44691 | H15: 10000 | I15: =J15*82 -> 211396 | J15: 2578 | K15: 44692 | L15: =H15-J15 -> 7422 | O15: TIRUPATI AGENCIES | P15: April | Q15: 6029 | R15: =Table35[[#This Row],[Amount Raised]]*82 -> 494378 | S15: 2578 | T15: =Table35[[#This Row],[Received Amount]]*82 -> 211396 | U15: 7422 | V15: KANERIYA OIL INDUSTRIES
A16: 15 | B16: NTC | C16: 44701 | D16: 44682 | E16: =TEXT(Project_Payments1617[[#This Row],[Invoice Month]],"mmmm") -> May | F16: 15 | G16: 44715 | H16: 10000 | I16: =J16*82 -> 205738 | J16: 2509 | K16: 44732 | L16: =H16-J16 -> 7491 | M16: TDS | O16: RAVI SALES | P16: May | Q16: 9086 | R16: =Table35[[#This Row],[Amount Raised]]*82 -> 745052 | S16: 2509 | T16: =Table35[[#This Row],[Received Amount]]*82 -> 205738 | U16: 7491 | V16: NTC
A17: 16 | B17: KQ BRO-SIS FOODS ENTERPRISE | C17: 44707 | D17: 44682 | E17: =TEXT(Project_Payments1617[[#This Row],[Invoice Month]],"mmmm") -> May | F17: 16 | G17: 44721 | H17: 10000 | I17: =J17*82 -> 621560 | J17: 7580 | K17: 44732 | L17: =H17-J17 -> 2420 | M17: TDS | O17: RAVI SALES | P17: May | Q17: 8722 | R17: =Table35[[#This Row],[Amount Raised]]*82 -> 715204 | S17: 7580 | T17: =Table35[[#This Row],[Received Amount]]*82 -> 621560 | U17: 2420 | V17: KQ BRO-SIS FOODS ENTERPRISE
A18: 17 | B18: NTC | C18: 44711 | D18: 44682 | E18: =TEXT(Project_Payments1617[[#This Row],[Invoice Month]],"mmmm") -> May | F18: 17 | G18: 44717 | H18: 10000 | I18: =J18*82 -> 425990 | J18: 5195 | K18: 44741 | L18: =H18-J18 -> 4805 | O18: JALARAM SALES AGENCY | P18: May | Q18: 5688 | R18: =Table35[[#This Row],[Amount Raised]]*82 -> 466416 | S18: 5195 | T18: =Table35[[#This Row],[Received Amount]]*82 -> 425990 | U18: 4805 | V18: NTC
A19: 18 | B19: NTC | C19: 44713 | D19: 44682 | E19: =TEXT(Project_Payments1617[[#This Row],[Invoice Month]],"mmmm") -> May | F19: 18 | G19: 44719 | H19: 10000 | I19: =J19*82 -> 632056 | J19: 7708 | K19: 44720 | L19: =H19-J19 -> 2292 | O19: KANERIYA OIL INDUSTRIES | P19: May | Q19: 6637 | R19: =Table35[[#This Row],[Amount Raised]]*82 -> 544234 | S19: 7708 | T19: =Table35[[#This Row],[Received Amount]]*82 -> 632056 | U19: 2292 | V19: NTC
A20: 19 | B20: JAY AMBE TRADERS | C20: 44714 | D20: 44682 | E20: =TEXT(Project_Payments1617[[#This Row],[Invoice Month]],"mmmm") -> May | F20: 19 | G20: 44728 | H20: 10000 | I20: =J20*82 -> 342678 | J20: 4179 | K20: 44715 | L20: =H20-J20 -> 5821 | M20: =2037026.96/26520 -> 76.810971 | O20: NTC | P20: May | Q20: 7562 | R20: =Table35[[#This Row],[Amount Raised]]*82 -> 620084 | S20: 4179 | T20: =Table35[[#This Row],[Received Amount]]*82 -> 342678 | U20: 5821 | V20: JAY AMBE TRADERS
A21: 20 | B21: RADHA DISTRIBUTORS | C21: 44715 | D21: 44682 | E21: =TEXT(Project_Payments1617[[#This Row],[Invoice Month]],"mmmm") -> May | F21: 20 | G21: 44729 | H21: 10000 | I21: =J21*82 -> 143500 | J21: 1750 | K21: 44726 | L21: =H21-J21 -> 8250 | O21: KQ BRO-SIS FOODS ENTERPRISE | P21: May | Q21: 4047 | R21: =Table35[[#This Row],[Amount Raised]]*82 -> 331854 | S21: 1750 | T21: =Table35[[#This Row],[Received Amount]]*82 -> 143500 | U21: 8250 | V21: RADHA DISTRIBUTORS
A22: 21 | B22: RADHA DISTRIBUTORS | C22: 44716 | D22: 44682 | E22: =TEXT(Project_Payments1617[[#This Row],[Invoice Month]],"mmmm") -> May | F22: 21 | G22: 44722 | H22: 10000 | I22: =J22*82 -> 408688 | J22: 4984 | K22: 44728 | L22: =H22-J22 -> 5016 | O22: NTC | P22: May | Q22: 4928 | R22: =Table35[[#This Row],[Amount Raised]]*82 -> 404096 | S22: 4984 | T22: =Table35[[#This Row],[Received Amount]]*82 -> 408688 | U22: 5016 | V22: RADHA DISTRIBUTORS
A23: 22 | B23: RADHA DISTRIBUTORS | C23: 44718 | D23: 44682 | E23: =TEXT(Project_Payments1617[[#This Row],[Invoice Month]],"mmmm") -> May | F23: 22 | G23: 44727 | H23: 10000 | I23: =J23*82 -> 244114 | J23: 2977 | K23: 44725 | L23: =H23-J23 -> 7023 | O23: JAY AMBE TRADERS | P23: May | Q23: 8723 | R23: =Table35[[#This Row],[Amount Raised]]*82 -> 715286 | S23: 2977 | T23: =Table35[[#This Row],[Received Amount]]*82 -> 244114 | U23: 7023 | V23: RADHA DISTRIBUTORS
A24: 23 | B24: SHAURYA ENTERPRISE | C24: 44734 | D24: 44713 | E24: =TEXT(Project_Payments1617[[#This Row],[Invoice Month]],"mmmm") -> June | F24: 23 | G24: 44748 | H24: 10000 | I24: =J24*82 -> 266254 | J24: 3247 | K24: 44762 | L24: =H24-J24 -> 6753 | M24: TDS | O24: NTC | P24: June | Q24: 1769 | R24: =Table35[[#This Row],[Amount Raised]]*82 -> 145058 | S24: 3247 | T24: =Table35[[#This Row],[Received Amount]]*82 -> 266254 | U24: 6753 | V24: SHAURYA ENTERPRISE
A25: 24 | B25: SHAURYA ENTERPRISE | C25: 44734 | D25: 44713 | E25: =TEXT(Project_Payments1617[[#This Row],[Invoice Month]],"mmmm") -> June | F25: 24 | G25: 44748 | H25: 10000 | I25: =J25*82 -> 458626 | J25: 5593 | K25: 44762 | L25: =H25-J25 -> 4407 | M25: TDS | O25: JAY AMBE TRADERS | P25: June | Q25: 6866 | R25: =Table35[[#This Row],[Amount Raised]]*82 -> 563012 | S25: 5593 | T25: =Table35[[#This Row],[Received Amount]]*82 -> 458626 | U25: 4407 | V25: SHAURYA ENTERPRISE
A26: 25 | B26: R C SALES | C26: 44736 | D26: May-June-2022 | E26: =TEXT(Project_Payments1617[[#This Row],[Invoice Month]],"mmmm") -> May-June-2022 | F26: 25 | G26: 44750 | H26: 10000 | I26: =J26*82 -> 492820 | J26: 6010 | K26: 44753 | L26: =H26-J26 -> 3990 | M26: =213322.58/2775 -> 76.873002 | O26: RADHA DISTRIBUTORS | P26: May-June-2022 | Q26: 2006 | R26: =Table35[[#This Row],[Amount Raised]]*82 -> 164492 | S26: 6010 | T26: =Table35[[#This Row],[Received Amount]]*82 -> 492820 | U26: 3990 | V26: R C SALES
A27: 26 | B27: SAMIR TRADIND CO. | C27: 44742 | D27: 44713 | E27: =TEXT(Project_Payments1617[[#This Row],[Invoice Month]],"mmmm") -> June | F27: 26 | G27: 44748 | H27: 10000 | I27: =J27*82 -> 412460 | J27: 5030 | K27: 44748 | L27: =H27-J27 -> 4970 | O27: RADHA DISTRIBUTORS | P27: June | Q27: 4543 | R27: =Table35[[#This Row],[Amount Raised]]*82 -> 372526 | S27: 5030 | T27: =Table35[[#This Row],[Received Amount]]*82 -> 412460 | U27: 4970 | V27: SAMIR TRADIND CO.
A28: 27 | B28: RAJBHARAT CASHEW COMPANY | C28: 44745 | D28: 44713 | E28: =TEXT(Project_Payments1617[[#This Row],[Invoice Month]],"mmmm") -> June | F28: 27 | G28: 44759 | H28: 10000 | I28: =J28*82 -> 317586 | J28: 3873 | K28: 44757 | L28: =H28-J28 -> 6127 | O28: RADHA DISTRIBUTORS | P28: June | Q28: 2434 | R28: =Table35[[#This Row],[Amount Raised]]*82 -> 199588 | S28: 3873 | T28: =Table35[[#This Row],[Received Amount]]*82 -> 317586 | U28: 6127 | V28: RAJBHARAT CASHEW COMPANY
A29: 28 | B29: KIRTI TRADING COMPANY | C29: 44746 | D29: 44713 | E29: =TEXT(Project_Payments1617[[#This Row],[Invoice Month]],"mmmm") -> June | F29: 28 | G29: 44752 | H29: 10000 | I29: =J29*82 -> 560552 | J29: 6836 | K29: 44762 | L29: =H29-J29 -> 3164 | O29: SHAURYA ENTERPRISE | P29: June | Q29: 8994 | R29: =Table35[[#This Row],[Amount Raised]]*82 -> 737508 | S29: 6836 | T29: =Table35[[#This Row],[Received Amount]]*82 -> 560552 | U29: 3164 | V29: KIRTI TRADING COMPANY
A30: 29 | B30: SHAH TOKARSHI TRIBHOVANDAS | C30: 44746 | D30: 44713 | E30: =TEXT(Project_Payments1617[[#This Row],[Invoice Month]],"mmmm") -> June | F30: 29 | G30: 44752 | H30: 10000 | I30: =J30*82 -> 653130 | J30: 7965 | K30: 44760 | L30: =H30-J30 -> 2035 | O30: R C SALES | P30: June | Q30: 2142 | R30: =Table35[[#This Row],[Amount Raised]]*82 -> 175644 | S30: 7965 | T30: =Table35[[#This Row],[Received Amount]]*82 -> 653130 | U30: 2035 | V30: SHAH TOKARSHI TRIBHOVANDAS
A31: 30 | B31: SAGAR SALES | C31: 44746 | D31: 44713 | E31: =TEXT(Project_Payments1617[[#This Row],[Invoice Month]],"mmmm") -> June | F31: 30 | G31: 44760 | H31: 10000 | I31: =J31*82 -> 293068 | J31: 3574 | K31: 44754 | L31: =H31-J31 -> 6426 | M31: =1996558.78/25300 -> 78.915367 | O31: SHAURYA ENTERPRISE | P31: June | Q31: 1408 | R31: =Table35[[#This Row],[Amount Raised]]*82 -> 115456 | S31: 3574 | T31: =Table35[[#This Row],[Received Amount]]*82 -> 293068 | U31: 6426 | V31: SAGAR SALES
A32: 31 | B32: RELIANCE RETAIL LIMITED | C32: 44764 | D32: 44743 | E32: =TEXT(Project_Payments1617[[#This Row],[Invoice Month]],"mmmm") -> July | F32: 31 | G32: 44778 | H32: 10000 | I32: =J32*82 -> 369328 | J32: 4504 | K32: 44792 | L32: =H32-J32 -> 5496 | M32: TDS | O32: R C SALES | P32: July | Q32: 2985 | R32: =Table35[[#This Row],[Amount Raised]]*82 -> 244770 | S32: 4504 | T32: =Table35[[#This Row],[Received Amount]]*82 -> 369328 | U32: 5496 | V32: RELIANCE RETAIL LIMITED
A33: 32 | B33: J.K.& CO. | C33: 44764 | D33: 44743 | E33: =TEXT(Project_Payments1617[[#This Row],[Invoice Month]],"mmmm") -> July | F33: 32 | G33: 44778 | H33: 10000 | I33: =J33*82 -> 235176 | J33: 2868 | K33: 44792 | L33: =H33-J33 -> 7132 | M33: TDS | O33: SAMIR TRADIND CO. | P33: July | Q33: 1315 | R33: =Table35[[#This Row],[Amount Raised]]*82 -> 107830 | S33: 2868 | T33: =Table35[[#This Row],[Received Amount]]*82 -> 235176 | U33: 7132 | V33: J.K.& CO.
A34: 33 | B34: PARTH ENTERPRISE | C34: 44769 | D34: June-July-2022 | E34: =TEXT(Project_Payments1617[[#This Row],[Invoice Month]],"mmmm") -> June-July-2022 | F34: 33 | G34: 44783 | H34: 10000 | I34: =J34*82 -> 134398 | J34: 1639 | K34: 44792 | L34: =H34-J34 -> 8361 | M34: =85591.3/1112.5 -> 76.936 | O34: RAJBHARAT CASHEW COMPANY | P34: June-July-2022 | Q34: 4342 | R34: =Table35[[#This Row],[Amount Raised]]*82 -> 356044 | S34: 1639 | T34: =Table35[[#This Row],[Received Amount]]*82 -> 134398 | U34: 8361 | V34: PARTH ENTERPRISE
A35: 34 | B35: SOMNATH RICE MILL | C35: 44769 | D35: June-July-2022 | E35: =TEXT(Project_Payments1617[[#This Row],[Invoice Month]],"mmmm") -> June-July-2022 | F35: 34 | G35: 44783 | H35: 10000 | I35: =J35*82 -> 284458 | J35: 3469 | K35: 44791 | L35: =H35-J35 -> 6531 | O35: KIRTI TRADING COMPANY | P35: June-July-2022 | Q35: 6874 | R35: =Table35[[#This Row],[Amount Raised]]*82 -> 563668 | S35: 3469 | T35: =Table35[[#This Row],[Received Amount]]*82 -> 284458 | U35: 6531 | V35: SOMNATH RICE MILL
A36: 35 | B36: SHIVAM AGRO PROCESSOR | C36: 44769 | D36: 44652 | E36: =TEXT(Project_Payments1617[[#This Row],[Invoice Month]],"mmmm") -> April | F36: 35 | G36: 44783 | H36: 10000 | I36: =J36*82 -> 372690 | J36: 4545 | K36: 44874 | L36: =H36-J36 -> 5455 | M36: 175976.14 Received single payment on 09-11-2022 | O36: SHAH TOKARSHI TRIBHOVANDAS | P36: April | Q36: 3899 | R36: =Table35[[#This Row],[Amount Raised]]*82 -> 319718 | S36: 4545 | T36: =Table35[[#This Row],[Received Amount]]*82 -> 372690 | U36: 5455 | V36: SHIVAM AGRO PROCESSOR
A37: 36 | B37: HARESHKUMAR HASSANAND | C37: 44769 | D37: 44682 | E37: =TEXT(Project_Payments1617[[#This Row],[Invoice Month]],"mmmm") -> May | F37: 36 | G37: 44783 | H37: 10000 | I37: =J37*82 -> 157850 | J37: 1925 | K37: 44874 | L37: =H37-J37 -> 8075 | M37: 175976.14 Received single payment on 09-11-2022 | O37: SAGAR SALES | P37: May | Q37: 6934 | R37: =Table35[[#This Row],[Amount Raised]]*82 -> 568588 | S37: 1925 | T37: =Table35[[#This Row],[Received Amount]]*82 -> 157850 | U37: 8075 | V37: HARESHKUMAR HASSANAND
A38: 37 | B38: RAJBHARAT CASHEW COMPANY | C38: 44769 | D38: 44713 | E38: =TEXT(Project_Payments1617[[#This Row],[Invoice Month]],"mmmm") -> June | F38: 37 | G38: 44783 | H38: 10000 | I38: =J38*82 -> 474124 | J38: 5782 | K38: 44874 | L38: =H38-J38 -> 4218 | M38: 175976.14 Received single payment on 09-11-2022 | O38: RELIANCE RETAIL LIMITED | P38: June | Q38: 6855 | R38: =Table35[[#This Row],[Amount Raised]]*82 -> 562110 | S38: 5782 | T38: =Table35[[#This Row],[Received Amount]]*82 -> 474124 | U38: 4218 | V38: RAJBHARAT CASHEW COMPANY
A39: 38 | B39: PARSHWANATH TRADERS | C39: 44773 | D39: 44743 | E39: =TEXT(Project_Payments1617[[#This Row],[Invoice Month]],"mmmm") -> July | F39: 38 | G39: 44779 | H39: 10000 | I39: =J39*82 -> 380234 | J39: 4637 | K39: 44777 | L39: =H39-J39 -> 5363 | O39: J.K.& CO. | P39: July | Q39: 8197 | R39: =Table35[[#This Row],[Amount Raised]]*82 -> 672154 | S39: 4637 | T39: =Table35[[#This Row],[Received Amount]]*82 -> 380234 | U39: 5363 | V39: PARSHWANATH TRADERS
A40: 39 | B40: RAJBHARAT CASHEW COMPANY | C40: 44775 | D40: 44743 | E40: =TEXT(Project_Payments1617[[#This Row],[Invoice Month]],"mmmm") -> July | F40: 39 | G40: 44789 | H40: 10000 | I40: =J40*82 -> 151700 | J40: 1850 | K40: 44785 | L40: =H40-J40 -> 8150 | M40: =1794784.5/22766 -> 78.836181 | O40: PARTH ENTERPRISE | P40: July | Q40: 1844 | R40: =Table35[[#This Row],[Amount Raised]]*82 -> 151208 | S40: 1850 | T40: =Table35[[#This Row],[Received Amount]]*82 -> 151700 | U40: 8150 | V40: RAJBHARAT CASHEW COMPANY
A41: 40 | B41: PARSHWANATH TRADERS | C41: 44776 | D41: 44743 | E41: =TEXT(Project_Payments1617[[#This Row],[Invoice Month]],"mmmm") -> July | F41: 40 | G41: 44790 | H41: 10000 | I41: =J41*82 -> 187288 | J41: 2284 | K41: 44791 | L41: =H41-J41 -> 7716 | O41: SOMNATH RICE MILL | P41: July | Q41: 3284 | R41: =Table35[[#This Row],[Amount Raised]]*82 -> 269288 | S41: 2284 | T41: =Table35[[#This Row],[Received Amount]]*82 -> 187288 | U41: 7716 | V41: PARSHWANATH TRADERS
A42: 41 | B42: RAJBHARAT CASHEW COMPANY | C42: 44777 | D42: 44743 | E42: =TEXT(Project_Payments1617[[#This Row],[Invoice Month]],"mmmm") -> July | F42: 41 | G42: 44783 | H42: 10000 | I42: =J42*82 -> 343252 | J42: 4186 | K42: 44795 | L42: =H42-J42 -> 5814 | O42: SHIVAM AGRO PROCESSOR | P42: July | Q42: 6415 | R42: =Table35[[#This Row],[Amount Raised]]*82 -> 526030 | S42: 4186 | T42: =Table35[[#This Row],[Received Amount]]*82 -> 343252 | U42: 5814 | V42: RAJBHARAT CASHEW COMPANY
A43: 42 | B43: KIRTI TRADING COMPANY | C43: 44777 | D43: 44743 | E43: =TEXT(Project_Payments1617[[#This Row],[Invoice Month]],"mmmm") -> July | F43: 42 | G43: 44791 | H43: 10000 | I43: =J43*82 -> 166460 | J43: 2030 | K43: 44888 | L43: =H43-J43 -> 7970 | M43: =41341.62/530 -> 78.003057 | O43: HARESHKUMAR HASSANAND | P43: July | Q43: 8971 | R43: =Table35[[#This Row],[Amount Raised]]*82 -> 735622 | S43: 2030 | T43: =Table35[[#This Row],[Received Amount]]*82 -> 166460 | U43: 7970 | V43: KIRTI TRADING COMPANY
A44: 43 | B44: SHAH TOKARSHI TRIBHOVANDAS | C44: 44782 | D44: 44743 | E44: =TEXT(Project_Payments1617[[#This Row],[Invoice Month]],"mmmm") -> July | F44: 43 | G44: 44791 | H44: 10000 | I44: =J44*82 -> 165886 | J44: 2023 | K44: 44784 | L44: =H44-J44 -> 7977 | O44: Zurick Artificial Intteligence, LLC | P44: July | Q44: 1934 | R44: =Table35[[#This Row],[Amount Raised]]*82 -> 158588 | S44: 2023 | T44: =Table35[[#This Row],[Received Amount]]*82 -> 165886 | U44: 7977 | V44: SAGAR SALES
A45: 44 | B45: SAGAR SALES | C45: 44785 | D45: Feb-Mar-Jul-22 | E45: =TEXT(Project_Payments1617[[#This Row],[Invoice Month]],"mmmm") -> Feb-Mar-Jul-22 | F45: 44 | G45: 44794 | H45: 10000 | I45: =J45*82 -> 205000 | J45: 2500 | K45: 44859 | L45: =H45-J45 -> 7500 | M45: =148898.97/1815 -> 82.038 | O45: Pest Control - Boruch Akbosh | P45: Feb-Mar-Jul-22 | Q45: 9155 | R45: =Table35[[#This Row],[Amount Raised]]*82 -> 750710 | S45: 2500 | T45: =Table35[[#This Row],[Received Amount]]*82 -> 205000 | U45: 7500 | V45: RELIANCE RETAIL LIMITED
A46: 45 | B46: RELIANCE RETAIL LIMITED | C46: 44785 | D46: 44743 | E46: =TEXT(Project_Payments1617[[#This Row],[Invoice Month]],"mmmm") -> July | F46: 45 | G46: 44794 | H46: 10000 | I46: =J46*82 -> 315372 | J46: 3846 | K46: 44795 | L46: =H46-J46 -> 6154 | O46: Conduit - Mukul Panchal | P46: July | Q46: 1160 | R46: =Table35[[#This Row],[Amount Raised]]*82 -> 95120 | S46: 3846 | T46: =Table35[[#This Row],[Received Amount]]*82 -> 315372 | U46: 6154 | V46: J.K.& CO.
A47: 46 | B47: J.K.& CO. | C47: 44785 | D47: 44743 | E47: =TEXT(Project_Payments1617[[#This Row],[Invoice Month]],"mmmm") -> July | F47: 46 | G47: 44794 | H47: 10000 | I47: =J47*82 -> 387532 | J47: 4726 | K47: 44826 | L47: =H47-J47 -> 5274 | O47: Mortgaze - Vishal Verma | P47: July | Q47: 2832 | R47: =Table35[[#This Row],[Amount Raised]]*82 -> 232224 | S47: 4726 | T47: =Table35[[#This Row],[Received Amount]]*82 -> 387532 | U47: 5274 | V47: PARTH ENTERPRISE
A48: 47 | B48: PARTH ENTERPRISE | C48: 44795 | D48: July-Aug-2022 | E48: =TEXT(Project_Payments1617[[#This Row],[Invoice Month]],"mmmm") -> July-Aug-2022 | F48: 47 | G48: 44809 | H48: 10000 | I48: =J48*82 -> 211150 | J48: 2575 | K48: 44817 | L48: =H48-J48 -> 7425 | O48: RAJBHARAT CASHEW COMPANY | P48: July-Aug-2022 | Q48: 5894 | R48: =Table35[[#This Row],[Amount Raised]]*82 -> 483308 | S48: 2575 | T48: =Table35[[#This Row],[Received Amount]]*82 -> 211150 | U48: 7425 | V48: Lumi
A49: 48 | B49: KIRTI TRADING COMPANY | C49: 44795 | D49: July-Aug-2022 | E49: =TEXT(Project_Payments1617[[#This Row],[Invoice Month]],"mmmm") -> July-Aug-2022 | F49: 48 | G49: 44809 | H49: 10000 | I49: =J49*82 -> 328574 | J49: 4007 | K49: 44880 | L49: =H49-J49 -> 5993 | M49: =119215.5/1500 -> 79.477 | O49: PARSHWANATH TRADERS | P49: July-Aug-2022 | Q49: 8028 | R49: =Table35[[#This Row],[Amount Raised]]*82 -> 658296 | S49: 4007 | T49: =Table35[[#This Row],[Received Amount]]*82 -> 328574 | U49: 5993 | V49: dedupe/VSI-Nationwide/Vsite-RemoteVal
A50: 49 | B50: SHAH TOKARSHI TRIBHOVANDAS | C50: 44796 | D50: 44774 | E50: =TEXT(Project_Payments1617[[#This Row],[Invoice Month]],"mmmm") -> August | F50: 49 | G50: 44811 | H50: 10000 | I50: =J50*82 -> 500036 | J50: 6098 | K50: 44824 | L50: =H50-J50 -> 3902 | M50: TDS | O50: RAJBHARAT CASHEW COMPANY | P50: August | Q50: 7910 | R50: =Table35[[#This Row],[Amount Raised]]*82 -> 648620 | S50: 6098 | T50: =Table35[[#This Row],[Received Amount]]*82 -> 500036 | U50: 3902 | V50: IFM
A51: 50 | B51: SAGAR SALES | C51: 44796 | D51: 44774 | E51: =TEXT(Project_Payments1617[[#This Row],[Invoice Month]],"mmmm") -> August | F51: 50 | G51: 44811 | H51: 10000 | I51: =J51*82 -> 481504 | J51: 5872 | K51: 44824 | L51: =H51-J51 -> 4128 | M51: TDS | O51: PARSHWANATH TRADERS | P51: August | Q51: 2613 | R51: =Table35[[#This Row],[Amount Raised]]*82 -> 214266 | S51: 5872 | T51: =Table35[[#This Row],[Received Amount]]*82 -> 481504 | U51: 4128 | V51: IFM
B52: RELIANCE RETAIL LIMITED | E52: =TEXT(Project_Payments1617[[#This Row],[Invoice Month]],"mmmm") -> January | I52: =J52*82 -> 0 | L52: =H52-J52 -> 0 | Q52: 7072 | R52: =Table35[[#This Row],[Amount Raised]]*82 -> 579904 | T52: =Table35[[#This Row],[Received Amount]]*82 -> 0
O53: Total | Q53: =SUM(Table35[Amount Raised]) -> 273566 | S53: =SUM(Table35[Received Amount]) -> 206183 | U53: =SUM(Table35[Pending Amount]) -> 283817
Q55: =Q53*82 -> 22432412

Sheet Other Expenses
A1: Client_Code | B1: Product_Code | C1: Payment_Type | D1: Payment_Ref_No. | E1: Payment_Date | F1: Instrument Date | G1: Dr_Ac_No | H1: Amount | I1: Bank_Code_Indicator | J1: Beneficiary_Code | K1: Beneficiary_Name | L1: Beneficiary_Bank | M1: Beneficiary_Branch / IFSC Code | N1: Beneficiary_Acc_No | O1: Exp. | P1: Sub. Exp. | Q1: Asset
A2: SCULPT01 | B2: VPAY | C2: IFT | E2: 21/04/2023 | G2: 8045843743 | H2: 3098 | I2: M | K2: Joshi Vivek Ashvinbhai | M2: KKBK0002564 | N2: 7411972445 | O2: Reimursement | P2: AntiVirus | Q2: =IF(OR(P2="Development Course",P2="Laptop Rent"),"Asset","Expense") -> Expense
A3: SCULPT01 | B3: VPAY | C3: NEFT | E3: 21/04/2023 | G3: 8045843743 | H3: 2800 | I3: M | K3: PAREKH PREMAL MAHESHKUMAR | M3: BARB0SOLAHM | N3: 29520100025300 | O3: Walfare | P3: Printer | Q3: Asset
A4: SCULPT01 | B4: VPAY | C4: NEFT | E4: 21/04/2023 | G4: 8045843743 | H4: 4000 | I4: M | K4: WALMIK NAMDEV MAGAR | M4: HDFC0004755 | N4: 50100369496477 | O4: Reimursement | P4: Scanners | Q4: Asset
A5: SCULPT01 | B5: VPAY | C5: NEFT | E5: 21/04/2023 | G5: 8045843743 | H5: 8700 | I5: M | K5: PRASHANT THAKKAR | M5: UTIB0000003 | N5: 911010030410284 | O5: Reimursement | P5: Printer | Q5: =IF(OR(P5="Development Course",P5="Laptop Rent"),"Asset","Expense") -> Expense
A6: SCULPT01 | B6: VPAY | C6: NEFT | E6: 21/04/2023 | G6: 8045843743 | H6: 48581 | I6: M | K6: CREDENT HR | M6: UBIN0905836 | N6: 058321010000015 | O6: Recruitment | P6: AntiVirus | Q6: =IF(OR(P6="Development Course",P6="Laptop Rent"),"Asset","Expense") -> Expense
A7: SCULPT01 | B7: VPAY | C7: NEFT | E7: 22/03/2023 | G7: 8045843743 | H7: 10000 | I7: M | K7: CREDENT HR | M7: UBIN0905836 | N7: 058321010000015 | O7: Recruitment | P7: AntiVirus | Q7: =IF(OR(P7="Development Course",P7="Laptop Rent"),"Asset","Expense") -> Expense
A8: SCULPT01 | B8: VPAY | C8: NEFT | E8: 15/03/2023 | G8: 8045843743 | H8: 5800 | I8: M | K8: CREDENT HR | M8: UBIN0905836 | N8: 058321010000015 | O8: Recruitment | P8: AntiVirus | Q8: =IF(OR(P8="Development Course",P8="Laptop Rent"),"Asset","Expense") -> Expense
A9: SCULPT01 | B9: VPAY | C9: NEFT | E9: 21/04/2023 | G9: 8045843743 | H9: 5000 | I9: M | K9: PAREKH PREMAL MAHESHKUMAR | M9: BARB0SOLAHM | N9: 29520100025300 | O9: Walfare | P9: Scanners | Q9: Asset
H10: =SUM(H2:H9) -> 87979
E11: Row Labels | F11: Sum of Amount
E12: Scanners | F12: 4000
E13: Asset | F13: 4000
E14: Printer | F14: 2800
E15: Asset | F15: 2800
E16: Grand Total | F16: 6800 | L16: Row Labels | M16: Sum of Amount
L17: Grand Total

Sheet Project wise revenue
A1: Sum of Received Amount | B1: Sum of Pending Amount
A2: 206183 | B2: 283817

Sheet Salary Paid as per project(Bar)
A1: Row Labels | B1: Sum of Salary to be Paid
A2: Accounts | B2: 46200
A3: Admin | B3: 29200
A4: Blitzz | B4: 693651
A5: Chatbot | B5: 78449
A6: dedupe/VSI-Nationwide/Vsite-RemoteVal | B6: 49800
A7: Genome | B7: 753720
A8: Hanson dodge | B8: 46200
A9: HR | B9: 158667
A10: IFM | B10: 167263
A11: Intelliante | B11: 96000
A12: Lumi | B12: 46200
A13: Marketing | B13: 8891
... A24: Grand Total | B24: 4068130

Sheet Dashboard
B1: FINANCIAL DASHBOARD
B3: Opening Balance | E3: Closing Balance | H3: Income VS Expense | L3: Income Raised | O3: Income Pending | T3: Total Income vs Expense
B4: =SBI!T15 -> 312297 | E4: =SBI!U15 -> 64408719 | H4: =(Kotak!H285+Project_income!Q55-SSPL!T146)-'Other Expenses'!H10 -> 16733595 | L4: =Project_income!Q53 -> 273566 | O4: =Project_income!U53 -> 283817 | T4: =GETPIVOTDATA("[Measures].[Sum of Salary to be Paid]",'Salary Paid as per project(Bar)'!$A$1) -> 4068130 | AL4: cccc
B16: Total Sallary Paid | I16: Total Assets
B17: =SSPL!T146 -> 5860838 | I17: =GETPIVOTDATA("Amount",'Other Expenses'!$E$11) -> 6800
